Workbook

Sheet Dados
A1: Link > | B1: PLANILHA para os MEMBROS: QUAIS AS DIFERENÇAS? E FORMAS DE UTILIZAR
A3: Empresa | B3: Código | C3: Atuação | D3: Quantidade total de ações | E3: Valor de mercado | F3: Lucro líquido estimado | G3: P/L projetado | H3: P/L médio (últ. 10 anos) | I3: Desvio do P/L da sua média | J3: CAGR lucros (últ. 5 anos) | K3: Dívida líquida/EBITDA | L3: Lucro por ação estimado | M3: Payout esperado | N3: Dividendo por ação bruto projetado | O3: Dividend Yield bruto estimado | P3: Cotação atual | Q3: Preço Teto | R3: Margem de segurança | S3: Frequência nos anúncios | T3: Meses que costumam anunciar dividendos | U3: Última atualização
A4: Irani | B4: RANI3 | C4: Papel e Celulose | D4: 221172300 | E4: =D4*P4 -> 2012667930 | F4: 215000000 | G4: =P4/L4 -> 9.3612462 | H4: 9.4 | I4: =(G4/H4-1) -> -0.0041227462 | J4: 0.33 | K4: 2.06 | L4: =F4/D4 -> 0.9720928 | M4: 0.7 | N4: =M4*L4 -> 0.68046496 | O4: =N4/P4 -> 0.074776369 | P4: =IFERROR(__xludf.DUMMYFUNCTION("GOOGLEFINANCE(""BVMF:RANI3"")"),9.1) -> 9.1 | Q4: 11 | R4: =1-(P4/Q4) -> 0.17272727 | S4: 5x por ano | T4: mar abr mai ago nov | U4: 46091
A5: Pagbank | B5: PAGS34 | C5: Serviços Financeiros | D5: =279705823*5 -> 1398529115 | E5: =D5*P5 -> 13831452947 | F5: 2550000000 | G5: =P5/L5 -> 5.4240992 | H5: 21.4 | I5: =(G5/H5-1) -> -0.74653742 | J5: 0.158 | K5: 0 | L5: =F5/D5 -> 1.8233442 | M5: 0.4714 | N5: =M5*L5 -> 0.85952447 | O5: =N5/P5 -> 0.08690844 | P5: =IFERROR(__xludf.DUMMYFUNCTION("GOOGLEFINANCE(""BVMF:PAGS34"")"),9.89) -> 9.89 | Q5: =6.5*L5 -> 11.851738 | R5: =1-(P5/Q5) -> 0.1655232 | S5: Trimestral | T5: fev jun set e dez | U5: 46091
A6: CSN Mineração | B6: CMIN3 | C6: Mineração | D6: 5432045700 | E6: =D6*P6 -> 26291101188 | F6: 2500000000 | G6: =P6/L6 -> 10.51644 | H6: 7.8 | I6: =(G6/H6-1) -> 0.3482616 | J6: -0.1125 | K6: -0.69 | L6: =F6/D6 -> 0.46023177 | M6: 0.75 | N6: =M6*L6 -> 0.34517383 | O6: =N6/P6 -> 0.071316906 | P6: =IFERROR(__xludf.DUMMYFUNCTION("GOOGLEFINANCE(""BVMF:CMIN3"")"),4.84) -> 4.84 | Q6: =N6/0.06 -> 5.7528971 | R6: =1-(P6/Q6) -> 0.15868476 | S6: Quadrimestral | T6: abr jul dez | U6: 46091
A7: Vulcabras | B7: VULC3 | C7: Calçados | D7: 312632756 | E7: =D7*P7 -> 5130303526 | F7: 600000000 | G7: =P7/L7 -> 8.5505059 | H7: 9.5 | I7: =(G7/H7-1) -> -0.09994675 | J7: 0.795 | K7: 0.9 | L7: =F7/D7 -> 1.9191847 | M7: 0.5 | N7: =M7*L7 -> 0.95959235 | O7: =N7/P7 -> 0.058476072 | P7: =IFERROR(__xludf.DUMMYFUNCTION("GOOGLEFINANCE(""BVMF:VULC3"")"),16.41) -> 16.41 | Q7: 19.5 | R7: =1-(P7/Q7) -> 0.15846154 | S7: Mensal | T7: jan a dezembro | U7: 46091
A8: Gerdau | B8: GGBR3 | C8: Siderurgia e Metalurgia | D8: 1989711987 | E8: =D8*P8 -> 31119095477 | F8: 3500000000 | G8: =P8/L8 -> 8.8911701 | H8: 10.5 | I8: =(G8/H8-1) -> -0.15322189 | J8: 0.067 | K8: 0.85 | L8: =F8/D8 -> 1.7590486 | M8: 0.65 | N8: =M8*L8 -> 1.1433816 | O8: =N8/P8 -> 0.073106238 | P8: =IFERROR(__xludf.DUMMYFUNCTION("GOOGLEFINANCE(""BVMF:GGBR3"")"),15.64) -> 15.64 | Q8: 18.5 | R8: =1-(P8/Q8) -> 0.15459459 | S8: Trimestral | T8: mar mai ago nov | U8: 46091
A9: Banco BMG | B9: BMGB4 | C9: Bancos | D9: 631845354 | E9: =D9*P9 -> 2988628524 | F9: 600000000 | G9: =P9/L9 -> 4.9810475 | H9: 8.3 | I9: =(G9/H9-1) -> -0.39987379 | J9: 0.0026 | K9: 0 | L9: =F9/D9 -> 0.94959945 | M9: 0.5 | N9: =M9*L9 -> 0.47479972 | O9: =N9/P9 -> 0.10038049 | P9: =IFERROR(__xludf.DUMMYFUNCTION("GOOGLEFINANCE(""BVMF:BMGB4"")"),4.73) -> 4.73 | Q9: =N9/0.085 -> 5.5858791 | R9: =1-(P9/Q9) -> 0.15322192 | S9: Trimestral | T9: abr jul out e dez | U9: 46091
A10: Kepler Weber | B10: KEPL3 | C10: Agronegócio | D10: 173367390 | E10: =D10*P10 -> 1333195229 | F10: 155000000 | G10: =P10/L10 -> 8.6012595 | H10: 9.8 | I10: =(G10/H10-1) -> -0.12232045 | J10: 0.173 | K10: -0.19 | L10: =F10/D10 -> 0.8940551 | M10: 0.6 | N10: =M10*L10 -> 0.53643306 | O10: =N10/P10 -> 0.069757225 | P10: =IFERROR(__xludf.DUMMYFUNCTION("GOOGLEFINANCE(""BVMF:KEPL3"")"),7.69) -> 7.69 | Q10: 9 | R10: =1-(P10/Q10) -> 0.14555556 | S10: Quadrimestral | T10: mar ago e out | U10: 46091
A11: Multiplan | B11: MULT3 | C11: Shoppings | D11: 488678545 | E11: =D11*P11 -> 14621262066 | F11: 1500000000 | G11: =P11/L11 -> 9.747508 | H11: 16 | I11: =(G11/H11-1) -> -0.39078075 | J11: 0.018 | K11: 2.28 | L11: =F11/D11 -> 3.0695025 | M11: 0.5 | N11: =M11*L11 -> 1.5347512 | O11: =N11/P11 -> 0.051295162 | P11: =IFERROR(__xludf.DUMMYFUNCTION("GOOGLEFINANCE(""BVMF:MULT3"")"),29.92) -> 29.92 | Q11: 35 | R11: =1-(P11/Q11) -> 0.14514286 | S11: Quadrimestral | T11: jun set e dez | U11: 46091
A12: Marcopolo | B12: POMO3 | C12: Industrial | D12: 1241439543 | E12: =D12*P12 -> 6852746277 | F12: 1200000000 | G12: =P12/L12 -> 5.7106219 | H12: 10.8 | I12: =(G12/H12-1) -> -0.47123871 | J12: 0.682 | K12: 0.85 | L12: =F12/D12 -> 0.96661977 | M12: 0.5 | N12: =M12*L12 -> 0.48330988 | O12: =N12/P12 -> 0.087556138 | P12: =IFERROR(__xludf.DUMMYFUNCTION("GOOGLEFINANCE(""BVMF:POMO3"")"),5.52) -> 5.52 | Q12: =N12/0.075 -> 6.4441318 | R12: =1-(P12/Q12) -> 0.14340672 | S12: Trimestral | T12: fev mai ago e nov | U12: 46091
A13: IRB | B13: IRBR3 | C13: Seguros | D13: 81843000 | E13: =D13*P13 -> 4529191620 | F13: 670000000 | G13: =P13/L13 -> 6.7599875 | H13: 15.8 | I13: =(G13/H13-1) -> -0.57215269 | J13: 0 | K13: 0 | L13: =F13/D13 -> 8.1864057 | M13: 0.5 | N13: =M13*L13 -> 4.0932028 | O13: =N13/P13 -> 0.073964634 | P13: =IFERROR(__xludf.DUMMYFUNCTION("GOOGLEFINANCE(""BVMF:IRBR3"")"),55.34) -> 55.34 | Q13: 64.55 | R13: =1-(P13/Q13) -> 0.14268009 | S13: Indefinido | T13: Indefinido | U13: 46091
A14: Porto Seguro | B14: PSSA3 | C14: Seguros | D14: 646586060 | E14: =D14*P14 -> 31883158619 | F14: 3700000000 | G14: =P14/L14 -> 8.6170699 | H14: 11 | I14: =(G14/H14-1) -> -0.21663001 | J14: 0.134 | K14: 0 | L14: =F14/D14 -> 5.7223628 | M14: 0.5 | N14: =M14*L14 -> 2.8611814 | O14: =N14/P14 -> 0.058024364 | P14: =IFERROR(__xludf.DUMMYFUNCTION("GOOGLEFINANCE(""BVMF:PSSA3"")"),49.31) -> 49.31 | Q14: =10*L14 -> 57.223628 | R14: =1-(P14/Q14) -> 0.13829301 | S14: Quadrimestral | T14: mar, jun e out | U14: 46091
A15: Klabin | B15: KLBN11 | C15: Papel e Celulose | D15: 1244049145 | E15: =D15*P15 -> 23773779161 | F15: 8600000000 | G15: =P15/L15 -> 2.7643929 | H15: 9.6 | I15: =(G15/H15-1) -> -0.7120424 | J15: 0.1046 | K15: 3.7 | L15: =F15/D15 -> 6.9129102 | M15: 0.15 | N15: =M15*L15 -> 1.0369365 | O15: =N15/P15 -> 0.054261461 | P15: =IFERROR(__xludf.DUMMYFUNCTION("GOOGLEFINANCE(""BVMF:KLBN11"")"),19.11) -> 19.11 | Q15: 22 | R15: =1-(P15/Q15) -> 0.13136364 | S15: Trimestral | T15: fev, mai, ago, nov | U15: 46091
A16: Banco Bradesco | B16: BBDC3 | C16: Bancos | D16: 10597012700 | E16: =D16*P16 -> 174002948534 | F16: 28000000000 | G16: =P16/L16 -> 6.214391 | H16: 9.2 | I16: =(G16/H16-1) -> -0.32452272 | J16: 0.0485 | K16: 0 | L16: =F16/D16 -> 2.6422541 | M16: 0.5 | N16: =M16*L16 -> 1.321127 | O16: =N16/P16 -> 0.080458407 | P16: =IFERROR(__xludf.DUMMYFUNCTION("GOOGLEFINANCE(""BVMF:BBDC3"")"),16.42) -> 16.42 | Q16: =N16/0.07 -> 18.873243 | R16: =1-(P16/Q16) -> 0.12998526 | S16: Semestral | T16: junho e dez | U16: 46091
A17: Klabin | B17: KLBN4 | C17: Papel e Celulose | D17: 6220245728 | E17: =D17*P17 -> 23823541138 | F17: 8600000000 | G17: =P17/L17 -> 2.7701792 | H17: 9.6 | I17: =(G17/H17-1) -> -0.71143967 | J17: 0.1046 | K17: 3.7 | L17: =F17/D17 -> 1.382582 | M17: 0.15 | N17: =M17*L17 -> 0.20738731 | O17: =N17/P17 -> 0.054148122 | P17: =IFERROR(__xludf.DUMMYFUNCTION("GOOGLEFINANCE(""BVMF:KLBN4"")"),3.83) -> 3.83 | Q17: 4.4 | R17: =1-(P17/Q17) -> 0.12954545 | S17: Trimestral | T17: fev, mai, ago, nov | U17: 46091
A18: Klabin | B18: KLBN3 | C18: Papel e Celulose | D18: 6220245728 | E18: =D18*P18 -> 23885743596 | F18: 8600000000 | G18: =P18/L18 -> 2.777412 | H18: 9.6 | I18: =(G18/H18-1) -> -0.71068625 | J18: 0.1046 | K18: 3.7 | L18: =F18/D18 -> 1.382582 | M18: 0.15 | N18: =M18*L18 -> 0.20738731 | O18: =N18/P18 -> 0.054007111 | P18: =IFERROR(__xludf.DUMMYFUNCTION("GOOGLEFINANCE(""BVMF:KLBN3"")"),3.84) -> 3.84 | Q18: 4.4 | R18: =1-(P18/Q18) -> 0.12727273 | S18: Trimestral | T18: fev, mai, ago, nov | U18: 46091
A19: Banco Mercantil | B19: BMEB3 | C19: Bancos | D19: 123728626 | E19: =D19*P19 -> 8751325717 | F19: 1200000000 | G19: =P19/L19 -> 7.2927714 | H19: 6.2 | I19: =(G19/H19-1) -> 0.17625346 | J19: 0.301 | K19: 0 | L19: =F19/D19 -> 9.6986448 | M19: 0.3 | N19: =M19*L19 -> 2.9095935 | O19: =N19/P19 -> 0.041136625 | P19: =IFERROR(__xludf.DUMMYFUNCTION("GOOGLEFINANCE(""BVMF:BMEB3"")"),70.73) -> 70.73 | Q19: 81 | R19: =1-(P19/Q19) -> 0.12679012 | S19: Semestral | T19: fevereiro e ago | U19: 46091
A20: BB Seguridade | B20: BBSE3 | C20: Seguros | D20: 1941214909 | E20: =D20*P20 -> 68039582560 | F20: 8650000000 | G20: =P20/L20 -> 7.8658477 | H20: 12.1 | I20: =(G20/H20-1) -> -0.34992994 | J20: 0.183 | K20: 0 | L20: =F20/D20 -> 4.4559724 | M20: 0.88 | N20: =M20*L20 -> 3.9212557 | O20: =N20/P20 -> 0.11187605 | P20: =IFERROR(__xludf.DUMMYFUNCTION("GOOGLEFINANCE(""BVMF:BBSE3"")"),35.05) -> 35.05 | Q20: 40 | R20: =1-(P20/Q20) -> 0.12375 | S20: Semestral | T20: fevereiro e agosto | U20: 46091
A21: Allos | B21: ALOS3 | C21: Shoppings | D21: 499180780 | E21: =D21*P21 -> 14436308158 | F21: 1500000000 | G21: =P21/L21 -> 9.6242054 | H21: 14.4 | I21: =(G21/H21-1) -> -0.3316524 | J21: 0.365 | K21: 1.8 | L21: =F21/D21 -> 3.0049234 | M21: 1.158 | N21: =M21*L21 -> 3.4797013 | O21: =N21/P21 -> 0.12032162 | P21: =IFERROR(__xludf.DUMMYFUNCTION("GOOGLEFINANCE(""BVMF:ALOS3"")"),28.92) -> 28.92 | Q21: 33 | R21: =1-(P21/Q21) -> 0.12363636 | S21: Mensal | T21: jan-dez | U21: 46091
A22: Metalúrgica Gerdau | B22: GOAU3 | C22: Siderurgia e Metalurgia | D22: 1324908144 | E22: =D22*P22 -> 10453525256 | F22: 1230000000 | G22: =P22/L22 -> 8.498801 | H22: 8.9 | I22: =(G22/H22-1) -> -0.045078537 | J22: 0.067 | K22: 0.85 | L22: =F22/D22 -> 0.92836625 | M22: 0.6 | N22: =M22*L22 -> 0.55701975 | O22: =N22/P22 -> 0.070598194 | P22: =IFERROR(__xludf.DUMMYFUNCTION("GOOGLEFINANCE(""BVMF:GOAU3"")"),7.89) -> 7.89 | Q22: 9 | R22: =1-(P22/Q22) -> 0.12333333 | S22: Trimestral | T22: mar mai ago nov | U22: 46091
A23: CSU | B23: CSUD3 | C23: Tecnologia | D23: 41280684 | E23: =D23*P23 -> 7.5956459e+08 | F23: 115000000 | G23: =P23/L23 -> 6.6049094 | H23: 10.1 | I23: =(G23/H23-1) -> -0.34604857 | J23: 0.147 | K23: -0.13 | L23: =F23/D23 -> 2.7858066 | M23: 0.5 | N23: =M23*L23 -> 1.3929033 | O23: =N23/P23 -> 0.075701265 | P23: =IFERROR(__xludf.DUMMYFUNCTION("GOOGLEFINANCE(""BVMF:CSUD3"")"),18.4) -> 18.4 | Q23: =7.5*L23 -> 20.893549 | R23: =1-(P23/Q23) -> 0.11934541 | S23: Trimestral | T23: mar abr jun set e dez | U23: 46093
A24: Dexxos | B24: DEXP3 | C24: Industrial | D24: 120961140 | E24: =D24*P24 -> 864872151 | F24: 130000000 | G24: =P24/L24 -> 6.6528627 | H24: 5.9 | I24: =(G24/H24-1) -> 0.12760385 | J24: 0.028 | K24: 0.08 | L24: =F24/D24 -> 1.0747253 | M24: 0.45 | N24: =M24*L24 -> 0.48362639 | O24: =N24/P24 -> 0.067640055 | P24: =IFERROR(__xludf.DUMMYFUNCTION("GOOGLEFINANCE(""BVMF:DEXP3"")"),7.15) -> 7.15 | Q24: 8.1 | R24: =1-(P24/Q24) -> 0.11728395 | S24: Semestral | T24: abril e dezembro | U24: 46091
A25: Banco Banrisul | B25: BRSR6 | C25: Bancos | D25: 408974000 | E25: =D25*P25 -> 6919840080 | F25: 1400000000 | G25: =P25/L25 -> 4.9427429 | H25: 6.5 | I25: =(G25/H25-1) -> -0.23957801 | J25: 0.011 | K25: 0 | L25: =F25/D25 -> 3.4232005 | M25: 0.45 | N25: =M25*L25 -> 1.5404402 | O25: =N25/P25 -> 0.091042566 | P25: =IFERROR(__xludf.DUMMYFUNCTION("GOOGLEFINANCE(""BVMF:BRSR6"")"),16.92) -> 16.92 | Q25: 19.15 | R25: =1-(P25/Q25) -> 0.11644909 | S25: Trimestral | T25: Mar, jun, set, dez | U25: 46091
A26: Tegma | B26: TGMA3 | C26: Logistica | D26: 66003000 | E26: =D26*P26 -> 2075794350 | F26: 220000000 | G26: =P26/L26 -> 9.4354289 | H26: 12.9 | I26: =(G26/H26-1) -> -0.26857141 | J26: 0.307 | K26: -0.35 | L26: =F26/D26 -> 3.3331818 | M26: 0.8 | N26: =M26*L26 -> 2.6665455 | O26: =N26/P26 -> 0.084786819 | P26: =IFERROR(__xludf.DUMMYFUNCTION("GOOGLEFINANCE(""BVMF:TGMA3"")"),31.45) -> 31.45 | Q26: =N26/0.075 -> 35.553939 | R26: =1-(P26/Q26) -> 0.11542854 | S26: Quadrimestral | T26: abr ago e nov | U26: 46091
A27: Banco Mercantil | B27: BMEB4 | C27: Bancos | D27: 123728626 | E27: =D27*P27 -> 9898290080 | F27: 1200000000 | G27: =P27/L27 -> 8.2485751 | H27: 6.2 | I27: =(G27/H27-1) -> 0.33041533 | J27: 0.301 | K27: 0 | L27: =F27/D27 -> 9.6986448 | M27: 0.3 | N27: =M27*L27 -> 2.9095935 | O27: =N27/P27 -> 0.036369918 | P27: =IFERROR(__xludf.DUMMYFUNCTION("GOOGLEFINANCE(""BVMF:BMEB4"")"),80.0) -> 80 | Q27: 90 | R27: =1-(P27/Q27) -> 0.11111111 | S27: Semestral | T27: fevereiro e ago | U27: 46091
A28: Tim | B28: TIMS3 | C28: Telecomunicações | D28: 2420598680 | E28: =D28*P28 -> 64387924888 | F28: 5400000000 | G28: =P28/L28 -> 11.92369 | H28: 14.8 | I28: =(G28/H28-1) -> -0.19434528 | J28: 0.145 | K28: -0.18 | L28: =F28/D28 -> 2.2308531 | M28: 1 | N28: =M28*L28 -> 2.2308531 | O28: =N28/P28 -> 0.083866657 | P28: =IFERROR(__xludf.DUMMYFUNCTION("GOOGLEFINANCE(""BVMF:TIMS3"")"),26.6) -> 26.6 | Q28: =N28/0.075 -> 29.744708 | R28: =1-(P28/Q28) -> 0.10572327 | S28: 5x por ano | T28: mar abr jun set dez | U28: 46091
A29: Wiz | B29: WIZC3 | C29: Seguros | D29: 159907000 | E29: =D29*P29 -> 1434365790 | F29: 200000000 | G29: =P29/L29 -> 7.171829 | H29: 8.6 | I29: =(G29/H29-1) -> -0.1660664 | J29: 0.111 | K29: 0.7 | L29: =F29/D29 -> 1.250727 | M29: 0.5 | N29: =M29*L29 -> 0.62536349 | O29: =N29/P29 -> 0.069717223 | P29: =IFERROR(__xludf.DUMMYFUNCTION("GOOGLEFINANCE(""BVMF:WIZC3"")"),8.97) -> 8.97 | Q29: =8*L29 -> 10.005816 | R29: =1-(P29/Q29) -> 0.10352138 | S29: Anual | T29: abril | U29: 46091
A30: Emae | B30: EMAE4 | C30: Energia | D30: 36947000 | E30: =D30*P30 -> 1644141500 | F30: 200000000 | G30: =P30/L30 -> 8.2207075 | H30: 14.6 | I30: =(G30/H30-1) -> -0.43693784 | J30: 0 | K30: -12.04 | L30: =F30/D30 -> 5.4131594 | M30: 0.4 | N30: =M30*L30 -> 2.1652638 | O30: =N30/P30 -> 0.048657613 | P30: =IFERROR(__xludf.DUMMYFUNCTION("GOOGLEFINANCE(""BVMF:EMAE4"")"),44.5) -> 44.5 | Q30: 49.5 | R30: =1-(P30/Q30) -> 0.1010101 | S30: Anual | T30: abril | U30: 46091
A31: Banco Santander | B31: SANB3 | C31: Bancos | D31: 7470968456 | E31: =D31*P31 -> 111915107471 | F31: 17400000000 | G31: =P31/L31 -> 6.4319027 | H31: 10.2 | I31: =(G31/H31-1) -> -0.3694213 | J31: -0.015 | K31: 0 | L31: =F31/D31 -> 2.3290153 | M31: 0.5 | N31: =M31*L31 -> 1.1645077 | O31: =N31/P31 -> 0.077737494 | P31: =IFERROR(__xludf.DUMMYFUNCTION("GOOGLEFINANCE(""BVMF:SANB3"")"),14.98) -> 14.98 | Q31: =N31/0.07 -> 16.635824 | R31: =1-(P31/Q31) -> 0.099533618 | S31: Trimestral | T31: fev, abr, julho e out | U31: 46091
A32: Banco Banese | B32: BGIP4 | C32: Bancos | D32: 21548228 | E32: =D32*P32 -> 8.1085982e+08 | F32: 150000000 | G32: =P32/L32 -> 5.4057321 | H32: 7.3 | I32: =(G32/H32-1) -> -0.25948875 | J32: 0.22 | K32: 0 | L32: =F32/D32 -> 6.9611292 | M32: 0.45 | N32: =M32*L32 -> 3.1325082 | O32: =N32/P32 -> 0.083244968 | P32: =IFERROR(__xludf.DUMMYFUNCTION("GOOGLEFINANCE(""BVMF:BGIP4"")"),37.63) -> 37.63 | Q32: =N32/0.075 -> 41.766775 | R32: =1-(P32/Q32) -> 0.099044645 | S32: Trimestral | T32: fev maio ago e nov | U32: 46091
A33: Grendene | B33: GRND3 | C33: Calçados | D33: 902160000 | E33: =D33*P33 -> 4095806400 | F33: 600000000 | G33: =P33/L33 -> 6.826344 | H33: 10.9 | I33: =(G33/H33-1) -> -0.37372991 | J33: 0.149 | K33: -2.38 | L33: =F33/D33 -> 0.6650705 | M33: 0.55 | N33: =M33*L33 -> 0.36578877 | O33: =N33/P33 -> 0.080570214 | P33: =IFERROR(__xludf.DUMMYFUNCTION("GOOGLEFINANCE(""BVMF:GRND3"")"),4.54) -> 4.54 | Q33: =5 -> 5 | R33: =1-(P33/Q33) -> 0.092 | S33: Quadrimestral | T33: maio ago e nov | U33: 46091
A34: Banco Santander | B34: SANB11 | C34: Bancos | D34: =7470968456/2 -> 3735484228 | E34: =D34*P34 -> 112886333370 | F34: 17400000000 | G34: =P34/L34 -> 6.4877203 | H34: 10.2 | I34: =(G34/H34-1) -> -0.36394899 | J34: -0.015 | K34: 0 | L34: =F34/D34 -> 4.6580306 | M34: 0.5 | N34: =M34*L34 -> 2.3290153 | O34: =N34/P34 -> 0.077068674 | P34: =IFERROR(__xludf.DUMMYFUNCTION("GOOGLEFINANCE(""BVMF:SANB11"")"),30.22) -> 30.22 | Q34: =N34/0.07 -> 33.271647 | R34: =1-(P34/Q34) -> 0.091719157 | S34: Trimestral | T34: fev, abr, julho e out | U34: 46091
A35: Mahle Metal Leve | B35: LEVE3 | C35: Automóveis e Motocicletas | D35: 135539000 | E35: =D35*P35 -> 4667963160 | F35: 630000000 | G35: =P35/L35 -> 7.4094653 | H35: 11.2 | I35: =(G35/H35-1) -> -0.3384406 | J35: 0.345 | K35: 0.87 | L35: =F35/D35 -> 4.6481087 | M35: 0.65 | N35: =M35*L35 -> 3.0212706 | O35: =N35/P35 -> 0.087725628 | P35: =IFERROR(__xludf.DUMMYFUNCTION("GOOGLEFINANCE(""BVMF:LEVE3"")"),34.44) -> 34.44 | Q35: =N35/0.08 -> 37.765883 | R35: =1-(P35/Q35) -> 0.088065805 | S35: Semestral | T35: abril e nov | U35: 46091
A36: Marcopolo | B36: POMO4 | C36: Industrial | D36: 1241439543 | E36: =D36*P36 -> 7312078908 | F36: 1200000000 | G36: =P36/L36 -> 6.0933991 | H36: 9.7 | I36: =(G36/H36-1) -> -0.37181453 | J36: 0.682 | K36: 0.85 | L36: =F36/D36 -> 0.96661977 | M36: 0.5 | N36: =M36*L36 -> 0.48330988 | O36: =N36/P36 -> 0.082056007 | P36: =IFERROR(__xludf.DUMMYFUNCTION("GOOGLEFINANCE(""BVMF:POMO4"")"),5.89) -> 5.89 | Q36: =N36/0.075 -> 6.4441318 | R36: =1-(P36/Q36) -> 0.085990136 | S36: Trimestral | T36: fev mai ago e nov | U36: 46091
A37: Banco Bradesco | B37: BBDC4 | C37: Bancos | D37: 10597012700 | E37: =D37*P37 -> 201237271173 | F37: 28000000000 | G37: =P37/L37 -> 7.1870454 | H37: 10.1 | I37: =(G37/H37-1) -> -0.28841135 | J37: 0.0118 | K37: 0 | L37: =F37/D37 -> 2.6422541 | M37: 0.55 | N37: =M37*L37 -> 1.4532397 | O37: =N37/P37 -> 0.076526579 | P37: =IFERROR(__xludf.DUMMYFUNCTION("GOOGLEFINANCE(""BVMF:BBDC4"")"),18.99) -> 18.99 | Q37: =N37/0.07 -> 20.760568 | R37: =1-(P37/Q37) -> 0.085285131 | S37: Semestral | T37: junho e dez | U37: 46091
A38: Odontoprev | B38: ODPV3 | C38: Seguros | D38: 545092900 | E38: =D38*P38 -> 7195226280 | F38: 595000000 | G38: =P38/L38 -> 12.092817 | H38: 19.4 | I38: =(G38/H38-1) -> -0.3766589 | J38: 0.1 | K38: -0.64 | L38: =F38/D38 -> 1.0915571 | M38: 0.95 | N38: =M38*L38 -> 1.0369792 | O38: =N38/P38 -> 0.07855903 | P38: =IFERROR(__xludf.DUMMYFUNCTION("GOOGLEFINANCE(""BVMF:ODPV3"")"),13.2) -> 13.2 | Q38: 14.4 | R38: =1-(P38/Q38) -> 0.083333333 | S38: 8x por ano | T38: mar abr mai jun ago set nov dez | U38: 46091
A39: BTG | B39: BPAC11 | C39: Bancos | D39: 11642630400 | E39: =D39*P39/3 -> 213875120448 | F39: 20000000000 | G39: =P39/L39 -> 10.693756 | H39: 17.4 | I39: =(G39/H39-1) -> -0.38541632 | J39: 0.1966 | K39: 0 | L39: =F39*3/D39 -> 5.1534746 | M39: 0.3 | N39: =M39*L39 -> 1.5460424 | O39: =N39/P39 -> 0.028053754 | P39: =IFERROR(__xludf.DUMMYFUNCTION("GOOGLEFINANCE(""BVMF:BPAC11"")"),55.11) -> 55.11 | Q39: 60 | R39: =1-(P39/Q39) -> 0.0815 | S39: Quadrimestral | T39: jan ago e dez | U39: 46091
A40: Log | B40: LOGG3 | C40: Exploração de imóveis | D40: 86999140 | E40: =D40*P40 -> 2289817365 | F40: 300000000 | G40: =P40/L40 -> 7.6327245 | H40: 8.6 | I40: =(G40/H40-1) -> -0.11247389 | J40: 0.2197 | K40: 0.7 | L40: =F40/D40 -> 3.4483099 | M40: 0.63 | N40: =M40*L40 -> 2.1724353 | O40: =N40/P40 -> 0.082539334 | P40: =IFERROR(__xludf.DUMMYFUNCTION("GOOGLEFINANCE(""BVMF:LOGG3"")"),26.32) -> 26.32 | Q40: 28.64 | R40: =1-(P40/Q40) -> 0.081005587 | S40: Trimestral | T40: fev maio ago e nov | U40: 46091
A41: MDias Branco | B41: MDIA3 | C41: Alimentos | D41: 335383253 | E41: =D41*P41 -> 7354954738 | F41: 800000000 | G41: =P41/L41 -> 9.1936934 | H41: 17.5 | I41: =(G41/H41-1) -> -0.47464609 | J41: 0.055 | K41: -0.5 | L41: =F41/D41 -> 2.3853308 | M41: 0.8 | N41: =M41*L41 -> 1.9082646 | O41: =N41/P41 -> 0.087016171 | P41: =IFERROR(__xludf.DUMMYFUNCTION("GOOGLEFINANCE(""BVMF:MDIA3"")"),21.93) -> 21.93 | Q41: =N41/0.08 -> 23.853308 | R41: =1-(P41/Q41) -> 0.080630658 | S41: Mensal | T41: jan a dezembro | U41: 46091
A42: Banco da Amazônia | B42: BAZA3 | C42: Bancos | D42: 56058000 | E42: =D42*P42 -> 4690372860 | F42: 900000000 | G42: =P42/L42 -> 5.2115254 | H42: 4.9 | I42: =(G42/H42-1) -> 0.063576612 | J42: 0.359 | K42: 0 | L42: =F42/D42 -> 16.0548 | M42: 0.35 | N42: =M42*L42 -> 5.6191801 | O42: =N42/P42 -> 0.06715884 | P42: =IFERROR(__xludf.DUMMYFUNCTION("GOOGLEFINANCE(""BVMF:BAZA3"")"),83.67) -> 83.67 | Q42: 90.94 | R42: =1-(P42/Q42) -> 0.079942819 | S42: Anual | T42: abril | U42: 46091
A43: Banco Santander | B43: SANB4 | C43: Bancos | D43: 7470968456 | E43: =D43*P43 -> 114604656115 | F43: 17400000000 | G43: =P43/L43 -> 6.5864745 | H43: 10.2 | I43: =(G43/H43-1) -> -0.35426721 | J43: -0.015 | K43: 0 | L43: =F43/D43 -> 2.3290153 | M43: 0.5 | N43: =M43*L43 -> 1.1645077 | O43: =N43/P43 -> 0.075913146 | P43: =IFERROR(__xludf.DUMMYFUNCTION("GOOGLEFINANCE(""BVMF:SANB4"")"),15.34) -> 15.34 | Q43: =N43/0.07 -> 16.635824 | R43: =1-(P43/Q43) -> 0.077893571 | S43: Trimestral | T43: fev, abr, julho e out | U43: 46091
A44: Suzano | B44: SUZB3 | C44: Papel e Celulose | D44: 1236099235 | E44: =D44*P44 -> 66007699149 | F44: 10000000000 | G44: =P44/L44 -> 6.6007699 | H44: 12.66 | I44: =(G44/H44-1) -> -0.47861217 | J44: 0.1094 | K44: 3.3 | L44: =F44/D44 -> 8.0899654 | M44: 0.3 | N44: =M44*L44 -> 2.4269896 | O44: =N44/P44 -> 0.045449244 | P44: =IFERROR(__xludf.DUMMYFUNCTION("GOOGLEFINANCE(""BVMF:SUZB3"")"),53.4) -> 53.4 | Q44: 57.7 | R44: =1-(P44/Q44) -> 0.074523397 | S44: Semestral | T44: abril e dez | U44: 46091
A45: Banco Pine | B45: PINE4 | C45: Bancos | D45: 258440362 | E45: =D45*P45 -> 2990154988 | F45: 450000000 | G45: =P45/L45 -> 6.6447889 | H45: 7.2 | I45: =(G45/H45-1) -> -0.077112658 | J45: 0.2986 | K45: 0 | L45: =F45/D45 -> 1.7412141 | M45: 0.45 | N45: =M45*L45 -> 0.78354634 | O45: =N45/P45 -> 0.067722242 | P45: =IFERROR(__xludf.DUMMYFUNCTION("GOOGLEFINANCE(""BVMF:PINE4"")"),11.57) -> 11.57 | Q45: 12.5 | R45: =1-(P45/Q45) -> 0.0744 | S45: Trimestral | T45: jan, abr, jul, out | U45: 46091
A46: Ferbasa | B46: FESA4 | C46: Siderurgia e Metalurgia | D46: 338867600 | E46: =D46*P46 -> 2511008916 | F46: 200000000 | G46: =P46/L46 -> 12.555045 | H46: 9.4 | I46: =(G46/H46-1) -> 0.33564304 | J46: 0.313 | K46: -1.33 | L46: =F46/D46 -> 0.59020101 | M46: 0.7 | N46: =M46*L46 -> 0.41314071 | O46: =N46/P46 -> 0.055754481 | P46: =IFERROR(__xludf.DUMMYFUNCTION("GOOGLEFINANCE(""BVMF:FESA4"")"),7.41) -> 7.41 | Q46: 8 | R46: =1-(P46/Q46) -> 0.07375 | S46: Quadrimestral | T46: jun set dez | U46: 46091
A47: Vale | B47: VALE3 | C47: Mineração | D47: 4437636744 | E47: =D47*P47 -> 347466957055 | F47: 53000000000 | G47: =P47/L47 -> 6.5559803 | H47: 10.3 | I47: =(G47/H47-1) -> -0.36349706 | J47: 0.023 | K47: 0.99 | L47: =F47/D47 -> 11.943294 | M47: 0.53 | N47: =M47*L47 -> 6.3299458 | O47: =N47/P47 -> 0.080842219 | P47: =IFERROR(__xludf.DUMMYFUNCTION("GOOGLEFINANCE(""BVMF:VALE3"")"),78.3) -> 78.3 | Q47: =N47/0.075 -> 84.399277 | R47: =1-(P47/Q47) -> 0.072266936 | S47: Quadrimestral | T47: mar, ago e dez | U47: 46091
A48: Romi | B48: ROMI3 | C48: Industrial | D48: 93171000 | E48: =D48*P48 -> 736050900 | F48: 90000000 | G48: =P48/L48 -> 8.1783433 | H48: 8.7 | I48: =(G48/H48-1) -> -0.059960536 | J48: -0.12 | K48: 3.04 | L48: =F48/D48 -> 0.9659658 | M48: 0.5 | N48: =M48*L48 -> 0.4829829 | O48: =N48/P48 -> 0.061137076 | P48: =IFERROR(__xludf.DUMMYFUNCTION("GOOGLEFINANCE(""BVMF:ROMI3"")"),7.9) -> 7.9 | Q48: 8.5 | R48: =1-(P48/Q48) -> 0.070588235 | S48: Trimestral | T48: mar jun set e dez | U48: 46091
A49: Banco ABC Brasil | B49: ABCB4 | C49: Bancos | D49: 244657000 | E49: =D49*P49 -> 6295024610 | F49: 1100000000 | G49: =P49/L49 -> 5.7227496 | H49: 6.7 | I49: =(G49/H49-1) -> -0.14585826 | J49: 0.275 | K49: 0 | L49: =F49/D49 -> 4.4960904 | M49: 0.5 | N49: =M49*L49 -> 2.2480452 | O49: =N49/P49 -> 0.087370588 | P49: =IFERROR(__xludf.DUMMYFUNCTION("GOOGLEFINANCE(""BVMF:ABCB4"")"),25.73) -> 25.73 | Q49: 27.63 | R49: =1-(P49/Q49) -> 0.068765834 | S49: Semestral | T49: junho e dez | U49: 46091
A50: BR Partners | B50: BRBI11 | C50: Serviços Financeiros | D50: =314987000/3 -> 1.0499567e+08 | E50: =D50*P50 -> 1974968490 | F50: 210000000 | G50: =P50/L50 -> 9.4046119 | H50: 9.1 | I50: =(G50/H50-1) -> 0.03347383 | J50: 0.2 | K50: 0 | L50: =F50/D50 -> 2.0000825 | M50: 0.8 | N50: =M50*L50 -> 1.600066 | O50: =N50/P50 -> 0.085064648 | P50: =IFERROR(__xludf.DUMMYFUNCTION("GOOGLEFINANCE(""BVMF:BRBI11"")"),18.81) -> 18.81 | Q50: =N50/0.08 -> 20.000825 | R50: =1-(P50/Q50) -> 0.059538814 | S50: Trimestral | T50: mar maio ago e nov | U50: 46091
A51: Stone | B51: STOC34 | C51: Serviços Financeiros | D51: 248904657 | E51: =D51*P51 -> 18244711358 | F51: 2760000000 | G51: =P51/L51 -> 6.6104027 | H51: 21.4 | I51: =(G51/H51-1) -> -0.69110268 | J51: 0.1 | K51: 0 | L51: =F51/D51 -> 11.088583 | M51: 0.7 | N51: =M51*L51 -> 7.7620082 | O51: =N51/P51 -> 0.1058937 | P51: =IFERROR(__xludf.DUMMYFUNCTION("GOOGLEFINANCE(""BVMF:STOC34"")"),73.3) -> 73.3 | Q51: =7*L51 -> 77.620082 | R51: =1-(P51/Q51) -> 0.055656762 | S51: Indefinido | T51: Indefinido | U51: 46094
A52: Banco Itau | B52: ITUB3 | C52: Bancos | D52: 10753776126 | E52: =D52*P52 -> 441227434450 | F52: 50000000000 | G52: =P52/L52 -> 8.8245487 | H52: 9.1 | I52: =(G52/H52-1) -> -0.030269375 | J52: 0.238 | K52: 0 | L52: =F52/D52 -> 4.6495296 | M52: 0.7 | N52: =M52*L52 -> 3.2546707 | O52: =N52/P52 -> 0.07932417 | P52: =IFERROR(__xludf.DUMMYFUNCTION("GOOGLEFINANCE(""BVMF:ITUB3"")"),41.03) -> 41.03 | Q52: =N52/0.075 -> 43.395609 | R52: =1-(P52/Q52) -> 0.05451264 | S52: Semestral | T52: fevereiro e ago | U52: 46091
A53: Comgás | B53: CGAS5 | C53: Oléo, gás e biocomb. | D53: 132521000 | E53: =D53*P53 -> 17466267800 | F53: 1600000000 | G53: =P53/L53 -> 10.916417 | H53: 11.4 | I53: =(G53/H53-1) -> -0.042419529 | J53: 0.0684 | K53: 1.93 | L53: =F53/D53 -> 12.073558 | M53: 0.85 | N53: =M53*L53 -> 10.262524 | O53: =N53/P53 -> 0.077864374 | P53: =IFERROR(__xludf.DUMMYFUNCTION("GOOGLEFINANCE(""BVMF:CGAS5"")"),131.8) -> 131.8 | Q53: =N53/0.074 -> 138.68276 | R53: =1-(P53/Q53) -> 0.049629546 | S53: Quadrimestral | T53: março, agosto e novembro | U53: 46091
A54: Itausa | B54: ITSA4 | C54: Holding | D54: 11213700000 | E54: =D54*P54 -> 147572292000 | F54: 17900000000 | G54: =P54/L54 -> 8.2442621 | H54: 8.7 | I54: =(G54/H54-1) -> -0.052383664 | J54: 0.164 | K54: 0 | L54: =F54/D54 -> 1.5962617 | M54: 0.65 | N54: =M54*L54 -> 1.0375701 | O54: =N54/P54 -> 0.078842714 | P54: =IFERROR(__xludf.DUMMYFUNCTION("GOOGLEFINANCE(""BVMF:ITSA4"")"),13.16) -> 13.16 | Q54: =N54/0.075 -> 13.834268 | R54: =1-(P54/Q54) -> 0.048738986 | S54: Semestral | T54: fevereiro e ago | U54: 46091
A55: Banco do Brasil | B55: BBAS3 | C55: Bancos | D55: 5708696148 | E55: =D55*P55 -> 135924055284 | F55: 24000000000 | G55: =P55/L55 -> 5.6635023 | H55: 6.4 | I55: =(G55/H55-1) -> -0.11507777 | J55: 0.132 | K55: 0 | L55: =F55/D55 -> 4.2041124 | M55: 0.3 | N55: =M55*L55 -> 1.2612337 | O55: =N55/P55 -> 0.052970756 | P55: =IFERROR(__xludf.DUMMYFUNCTION("GOOGLEFINANCE(""BVMF:BBAS3"")"),23.81) -> 23.81 | Q55: 25 | R55: =1-(P55/Q55) -> 0.0476 | S55: 8x por ano | T55: mar jun set e dez | U55: 46091
A56: Caixa Seguridade | B56: CXSE3 | C56: Seguros | D56: 3000000000 | E56: =D56*P56 -> 54420000000 | F56: 4700000000 | G56: =P56/L56 -> 11.578723 | H56: 12.4 | I56: =(G56/H56-1) -> -0.066231984 | J56: 0.197 | K56: 0 | L56: =F56/D56 -> 1.5666667 | M56: 0.9 | N56: =M56*L56 -> 1.41 | O56: =N56/P56 -> 0.077728776 | P56: =IFERROR(__xludf.DUMMYFUNCTION("GOOGLEFINANCE(""BVMF:CXSE3"")"),18.14) -> 18.14 | Q56: =N56/0.075 -> 18.8 | R56: =1-(P56/Q56) -> 0.035106383 | S56: Trimestral | T56: jan, abr, ago e nov | U56: 46091
A57: SLC Agrícola | B57: SLCE3 | C57: Agronegócio | D57: 496621582 | E57: =D57*P57 -> 8939188476 | F57: 840000000 | G57: =P57/L57 -> 10.641891 | H57: 10.8 | I57: =(G57/H57-1) -> -0.014639718 | J57: 0.084 | K57: 2.3 | L57: =F57/D57 -> 1.6914287 | M57: 0.5 | N57: =M57*L57 -> 0.84571435 | O57: =N57/P57 -> 0.046984131 | P57: =IFERROR(__xludf.DUMMYFUNCTION("GOOGLEFINANCE(""BVMF:SLCE3"")"),18.0) -> 18 | Q57: 18.64 | R57: =1-(P57/Q57) -> 0.034334764 | S57: Semestral | T57: abril e dezembro | U57: 46093
A58: Sanepar | B58: SAPR4 | C58: Saneamento | D58: 1511205519 | E58: =D58*P58 -> 11681618662 | F58: 1700000000 | G58: =P58/L58 -> 6.8715404 | H58: 7 | I58: =(G58/H58-1) -> -0.018351373 | J58: 0.178 | K58: 1.7 | L58: =F58/D58 -> 1.1249297 | M58: 0.35 | N58: =M58*L58 -> 0.3937254 | O58: =N58/P58 -> 0.050934722 | P58: =IFERROR(__xludf.DUMMYFUNCTION("GOOGLEFINANCE(""BVMF:SAPR4"")"),7.73) -> 7.73 | Q58: 8 | R58: =1-(P58/Q58) -> 0.03375 | S58: Semestral | T58: jun e dez | U58: 46091
A59: Banco Itau | B59: ITUB4 | C59: Bancos | D59: 10753776126 | E59: =D59*P59 -> 455960107742 | F59: 50000000000 | G59: =P59/L59 -> 9.1192022 | H59: 10 | I59: =(G59/H59-1) -> -0.088079785 | J59: 0.238 | K59: 0 | L59: =F59/D59 -> 4.6495296 | M59: 0.65 | N59: =M59*L59 -> 3.0221942 | O59: =N59/P59 -> 0.071278165 | P59: =IFERROR(__xludf.DUMMYFUNCTION("GOOGLEFINANCE(""BVMF:ITUB4"")"),42.4) -> 42.4 | Q59: =N59/0.07 -> 43.174203 | R59: =1-(P59/Q59) -> 0.017932076 | S59: Semestral | T59: fevereiro e ago | U59: 46091
A60: Bradespar | B60: BRAP4 | C60: Holding | D60: 393097000 | E60: =D60*P60 -> 8687443700 | F60: 1670000000 | G60: =P60/L60 -> 5.2020621 | H60: 8.7 | I60: =(G60/H60-1) -> -0.40206183 | J60: -0.059 | K60: -0.64 | L60: =F60/D60 -> 4.2483153 | M60: 0.45 | N60: =M60*L60 -> 1.9117419 | O60: =N60/P60 -> 0.086504158 | P60: =IFERROR(__xludf.DUMMYFUNCTION("GOOGLEFINANCE(""BVMF:BRAP4"")"),22.1) -> 22.1 | Q60: =N60/0.085 -> 22.491081 | R60: =1-(P60/Q60) -> 0.017388271 | S60: Semestral | T60: abril e novembro | U60: 46091
A61: Sanepar | B61: SAPR11 | C61: Saneamento | D61: =1511205519/5 -> 3.022411e+08 | E61: =D61*P61 -> 11929456367 | F61: 1700000000 | G61: =P61/L61 -> 7.0173273 | H61: 7 | I61: =(G61/H61-1) -> 0.002475325 | J61: 0.178 | K61: 1.7 | L61: =F61/D61 -> 5.6246486 | M61: 0.3 | N61: =M61*L61 -> 1.6873946 | O61: =N61/P61 -> 0.042751319 | P61: =IFERROR(__xludf.DUMMYFUNCTION("GOOGLEFINANCE(""BVMF:SAPR11"")"),39.47) -> 39.47 | Q61: 40 | R61: =1-(P61/Q61) -> 0.01325 | S61: Semestral | T61: jun e dez | U61: 46091
A62: Brasilagro | B62: AGRO3 | C62: Agronegócio | D62: 99615457 | E62: =D62*P62 -> 2221424691 | F62: 100000000 | G62: =P62/L62 -> 22.214247 | H62: 10 | I62: =(G62/H62-1) -> 1.2214247 | J62: 0.228 | K62: 1.7 | L62: =F62/D62 -> 1.0038603 | M62: 0.65 | N62: =M62*L62 -> 0.65250918 | O62: =N62/P62 -> 0.029260501 | P62: =IFERROR(__xludf.DUMMYFUNCTION("GOOGLEFINANCE(""BVMF:AGRO3"")"),22.3) -> 22.3 | Q62: 22.48 | R62: =1-(P62/Q62) -> 0.0080071174 | S62: Anual | T62: outubro | U62: 46091
A63: Grazziotin | B63: CGRA4 | C63: Varejo | D63: 23601907 | E63: =D63*P63 -> 6.5282875e+08 | F63: 100000000 | G63: =P63/L63 -> 6.5282875 | H63: 7.3 | I63: =(G63/H63-1) -> -0.10571404 | J63: 0.078 | K63: -1.63 | L63: =F63/D63 -> 4.2369458 | M63: 0.5 | N63: =M63*L63 -> 2.1184729 | O63: =N63/P63 -> 0.076589764 | P63: =IFERROR(__xludf.DUMMYFUNCTION("GOOGLEFINANCE(""BVMF:CGRA4"")"),27.66) -> 27.66 | Q63: =6.5*L63 -> 27.540147 | R63: =1-(P63/Q63) -> -0.0043519194 | S63: Semestral | T63: jun e dez | U63: 46091
A64: CPFL Energia | B64: CPFE3 | C64: Energia | D64: 1152254440 | E64: =D64*P64 -> 55481051286 | F64: 5500000000 | G64: =P64/L64 -> 10.087464 | H64: 13 | I64: =(G64/H64-1) -> -0.22404124 | J64: 0.087 | K64: 2.07 | L64: =F64/D64 -> 4.7732513 | M64: 0.781 | N64: =M64*L64 -> 3.7279093 | O64: =N64/P64 -> 0.07742283 | P64: =IFERROR(__xludf.DUMMYFUNCTION("GOOGLEFINANCE(""BVMF:CPFE3"")"),48.15) -> 48.15 | Q64: =L64*10 -> 47.732513 | R64: =1-(P64/Q64) -> -0.008746387 | S64: Semestral | T64: abril e agosto | U64: 46091
A65: JHSF | B65: JHSF3 | C65: Imobiliário | D65: 658316448 | E65: =D65*P65 -> 5661521453 | F65: 600000000 | G65: =P65/L65 -> 9.4358691 | H65: 5.4 | I65: =(G65/H65-1) -> 0.74738316 | J65: 0.1529 | K65: 1.86 | L65: =F65/D65 -> 0.91141578 | M65: 0.9 | N65: =M65*L65 -> 0.8202742 | O65: =N65/P65 -> 0.095380721 | P65: =IFERROR(__xludf.DUMMYFUNCTION("GOOGLEFINANCE(""BVMF:JHSF3"")"),8.6) -> 8.6 | Q65: 8.5 | R65: =1-(P65/Q65) -> -0.011764706 | S65: Mensal | T65: jan a dezembro | U65: 46091
A66: Alupar | B66: ALUP11 | C66: Energia | D66: =914275704/3 -> 304758568 | E66: =D66*P66 -> 10508075425 | F66: 950000000 | G66: =P66/L66 -> 11.061132 | H66: 11.2 | I66: =(G66/H66-1) -> -0.012398926 | J66: -0.023 | K66: 3.5 | L66: =F66/D66 -> 3.1172216 | M66: 0.65 | N66: =M66*L66 -> 2.0261941 | O66: =N66/P66 -> 0.058764329 | P66: =IFERROR(__xludf.DUMMYFUNCTION("GOOGLEFINANCE(""BVMF:ALUP11"")"),34.48) -> 34.48 | Q66: =N66/0.06 -> 33.769901 | R66: =1-(P66/Q66) -> -0.021027572 | S66: Trimestral | T66: abr mai ago nov | U66: 46091
A67: Banestes | B67: BEES3 | C67: Bancos | D67: 347504000 | E67: =D67*P67 -> 2988534400 | F67: 450000000 | G67: =P67/L67 -> 6.6411876 | H67: 7.2 | I67: =(G67/H67-1) -> -0.07761284 | J67: 0.06 | K67: 0 | L67: =F67/D67 -> 1.2949491 | M67: 0.42 | N67: =M67*L67 -> 0.54387863 | O67: =N67/P67 -> 0.063241701 | P67: =IFERROR(__xludf.DUMMYFUNCTION("GOOGLEFINANCE(""BVMF:BEES3"")"),8.6) -> 8.6 | Q67: 8.4 | R67: =1-(P67/Q67) -> -0.023809524 | S67: Mensal | T67: jan-dez | U67: 46091
A68: CEB | B68: CEBR6 | C68: Energia | D68: 72082000 | E68: =D68*P68 -> 2235983640 | F68: 200000000 | G68: =P68/L68 -> 11.179918 | H68: 7.1 | I68: =(G68/H68-1) -> 0.57463637 | J68: 0.073 | K68: -3.17 | L68: =F68/D68 -> 2.7746178 | M68: 0.778 | N68: =M68*L68*1.1 -> 2.3745179 | O68: =N68/P68 -> 0.076547966 | P68: =IFERROR(__xludf.DUMMYFUNCTION("GOOGLEFINANCE(""BVMF:CEBR6"")"),31.02) -> 31.02 | Q68: =N68/0.08 -> 29.681474 | R68: =1-(P68/Q68) -> -0.04509635 | S68: Semestral | T68: Abril e novembro | U68: 46091
A69: Shulz | B69: SHUL4 | C69: Bens Industriais | D69: 356964439 | E69: =D69*P69 -> 1874063305 | F69: 200000000 | G69: =P69/L69 -> 9.3703165 | H69: 9.2 | I69: =(G69/H69-1) -> 0.018512666 | J69: 0.139 | K69: 0.12 | L69: =F69/D69 -> 0.5602799 | M69: 0.5 | N69: =M69*L69 -> 0.28013995 | O69: =N69/P69 -> 0.05335999 | P69: =IFERROR(__xludf.DUMMYFUNCTION("GOOGLEFINANCE(""BVMF:SHUL4"")"),5.25) -> 5.25 | Q69: 5 | R69: =1-(P69/Q69) -> -0.05 | S69: Trimestral | T69: abr jun set dez | U69: 46091
A70: Petrobras | B70: PETR4 | C70: Oléo, gás e biocomb. | D70: 12888732761 | E70: =D70*P70 -> 575739692434 | F70: 73000000000 | G70: =P70/L70 -> 7.8868451 | H70: 6.2 | I70: =(G70/H70-1) -> 0.27207179 | J70: 0.656 | K70: 1.53 | L70: =F70/D70 -> 5.6638617 | M70: 0.45 | N70: =M70*L70 -> 2.5487378 | O70: =N70/P70 -> 0.057057035 | P70: =IFERROR(__xludf.DUMMYFUNCTION("GOOGLEFINANCE(""BVMF:PETR4"")"),44.67) -> 44.67 | Q70: 42 | R70: =1-(P70/Q70) -> -0.063571429 | S70: Trimestral | T70: abr mai ago nov | U70: 46091
A71: Fleury | B71: FLRY3 | C71: Saúde | D71: 544279713 | E71: =D71*P71 -> 8376464783 | F71: 680000000 | G71: =P71/L71 -> 12.318331 | H71: 25 | I71: =(G71/H71-1) -> -0.50726678 | J71: 0.178 | K71: 1.51 | L71: =F71/D71 -> 1.2493576 | M71: 0.75 | N71: =M71*L71 -> 0.93701821 | O71: =N71/P71 -> 0.060884874 | P71: =IFERROR(__xludf.DUMMYFUNCTION("GOOGLEFINANCE(""BVMF:FLRY3"")"),15.39) -> 15.39 | Q71: =N71/0.065 -> 14.415665 | R71: =1-(P71/Q71) -> -0.067588649 | S71: Semestral | T71: março e dezembro | U71: 46091
A72: Taesa | B72: TAEE3 | C72: Energia | D72: 1033496721 | E72: =D72*P72 -> 14313929586 | F72: 1270000000 | G72: =P72/L72 -> 11.270811 | H72: 8.6 | I72: =(G72/H72-1) -> 0.31055938 | J72: -0.058 | K72: 4.1 | L72: =F72/D72 -> 1.228838 | M72: 0.95 | N72: =M72*L72 -> 1.1673961 | O72: =N72/P72 -> 0.084288524 | P72: =IFERROR(__xludf.DUMMYFUNCTION("GOOGLEFINANCE(""BVMF:TAEE3"")"),13.85) -> 13.85 | Q72: =N72/0.09 -> 12.971067 | R72: =1-(P72/Q72) -> -0.067761013 | S72: Trimestral | T72: mai, ago, nov, dez | U72: 46091
A73: Unifique | B73: FIQE3 | C73: Telecomunicações | D73: 399087000 | E73: =D73*P73 -> 2139106320 | F73: 200000000 | G73: =P73/L73 -> 10.695532 | H73: 9.7 | I73: =(G73/H73-1) -> 0.10263212 | J73: 0.2 | K73: 0.84 | L73: =F73/D73 -> 0.50114386 | M73: 0.5 | N73: =M73*L73 -> 0.25057193 | O73: =N73/P73 -> 0.046748494 | P73: =IFERROR(__xludf.DUMMYFUNCTION("GOOGLEFINANCE(""BVMF:FIQE3"")"),5.36) -> 5.36 | Q73: =10*L73 -> 5.0114386 | R73: =1-(P73/Q73) -> -0.06955316 | S73: Quadrimestral | T73: fev junho e dez | U73: 46091
A74: Petroreconcâvo | B74: RECV3 | C74: Oléo, gás e biocomb. | D74: 292973655 | E74: =D74*P74 -> 3761781730 | F74: 440000000 | G74: =P74/L74 -> 8.5495039 | H74: 9.3 | I74: =(G74/H74-1) -> -0.080698502 | J74: 0.3173 | K74: 1 | L74: =F74/D74 -> 1.5018415 | M74: 0.5 | N74: =M74*L74 -> 0.75092076 | O74: =N74/P74 -> 0.058482925 | P74: =IFERROR(__xludf.DUMMYFUNCTION("GOOGLEFINANCE(""BVMF:RECV3"")"),12.84) -> 12.84 | Q74: 12 | R74: =1-(P74/Q74) -> -0.07 | S74: Semestral | T74: maio e dez | U74: 46091
A75: B3 | B75: B3SA3 | C75: Serviços Financeiros | D75: 5168573066 | E75: =D75*P75 -> 87245513354 | F75: 5700000000 | G75: =P75/L75 -> 15.30623 | H75: 21 | I75: =(G75/H75-1) -> -0.27113189 | J75: 0.147 | K75: 0.05 | L75: =F75/D75 -> 1.1028189 | M75: 1 | N75: =M75*L75 -> 1.1028189 | O75: =N75/P75 -> 0.065332872 | P75: =IFERROR(__xludf.DUMMYFUNCTION("GOOGLEFINANCE(""BVMF:B3SA3"")"),16.88) -> 16.88 | Q75: =N75/0.07 -> 15.754556 | R75: =1-(P75/Q75) -> -0.071436129 | S75: Trimestral | T75: mar jun set dez | U75: 46091
A76: Axia Energia | B76: AXIA3 | C76: Energia | D76: 2855268322 | E76: =D76*P76 -> 165605562676 | F76: 12000000000 | G76: =P76/L76 -> 13.800464 | H76: 9.3 | I76: =(G76/H76-1) -> 0.48392081 | J76: 0.0075 | K76: 1.8 | L76: =F76/D76 -> 4.2027574 | M76: 0.85 | N76: =M76*L76 -> 3.5723438 | O76: =N76/P76 -> 0.061592134 | P76: =IFERROR(__xludf.DUMMYFUNCTION("GOOGLEFINANCE(""BVMF:AXIA3"")"),58.0) -> 58 | Q76: 54 | R76: =1-(P76/Q76) -> -0.074074074 | S76: Semestral | T76: Abril e dezembro | U76: 46091
A77: CEB | B77: CEBR5 | C77: Energia | D77: 72082000 | E77: =D77*P77 -> 2100469480 | F77: 200000000 | G77: =P77/L77 -> 10.502347 | H77: 7.1 | I77: =(G77/H77-1) -> 0.47920386 | J77: 0.073 | K77: -3.17 | L77: =F77/D77 -> 2.7746178 | M77: 0.778 | N77: =M77*L77 -> 2.1586526 | O77: =N77/P77 -> 0.074078677 | P77: =IFERROR(__xludf.DUMMYFUNCTION("GOOGLEFINANCE(""BVMF:CEBR5"")"),29.14) -> 29.14 | Q77: =N77/0.08 -> 26.983158 | R77: =1-(P77/Q77) -> -0.079932895 | S77: Semestral | T77: Abril e novembro | U77: 46091
A78: Taesa | B78: TAEE11 | C78: Energia | D78: =1033496721/3 -> 344498907 | E78: =D78*P78 -> 14537853875 | F78: 1270000000 | G78: =P78/L78 -> 11.447129 | H78: 8.6 | I78: =(G78/H78-1) -> 0.33106152 | J78: -0.058 | K78: 4.1 | L78: =F78/D78 -> 3.6865139 | M78: 0.95 | N78: =M78*L78 -> 3.5021882 | O78: =N78/P78 -> 0.082990241 | P78: =IFERROR(__xludf.DUMMYFUNCTION("GOOGLEFINANCE(""BVMF:TAEE11"")"),42.2) -> 42.2 | Q78: =N78/0.09 -> 38.913202 | R78: =1-(P78/Q78) -> -0.084464856 | S78: Trimestral | T78: mai, ago, nov, dez | U78: 46091
A79: Taesa | B79: TAEE4 | C79: Energia | D79: 1033496721 | E79: =D79*P79 -> 14644648537 | F79: 1270000000 | G79: =P79/L79 -> 11.531219 | H79: 8.6 | I79: =(G79/H79-1) -> 0.34083946 | J79: -0.058 | K79: 4.1 | L79: =F79/D79 -> 1.228838 | M79: 0.95 | N79: =M79*L79 -> 1.1673961 | O79: =N79/P79 -> 0.082385043 | P79: =IFERROR(__xludf.DUMMYFUNCTION("GOOGLEFINANCE(""BVMF:TAEE4"")"),14.17) -> 14.17 | Q79: =N79/0.09 -> 12.971067 | R79: =1-(P79/Q79) -> -0.092431304 | S79: Trimestral | T79: mai, ago, nov, dez | U79: 46091
A80: Celesc | B80: CLSC4 | C80: Energia | D80: 38572000 | E80: =D80*P80 -> 5583682720 | F80: 850000000 | G80: =P80/L80 -> 6.5690385 | H80: 5.6 | I80: =(G80/H80-1) -> 0.17304259 | J80: 0.073 | K80: 2.2 | L80: =F80/D80 -> 22.036711 | M80: 0.35 | N80: =M80*L80 -> 7.7128487 | O80: =N80/P80 -> 0.053280248 | P80: =IFERROR(__xludf.DUMMYFUNCTION("GOOGLEFINANCE(""BVMF:CLSC4"")"),144.76) -> 144.76 | Q80: =6*L80 -> 132.22026 | R80: =1-(P80/Q80) -> -0.094839749 | S80: 5x por ano | T80: mar abr jun set dez | U80: 46091
A81: Cemig | B81: CMIG4 | C81: Energia | D81: 2861781207 | E81: =D81*P81 -> 33540075746 | F81: 3800000000 | G81: =P81/L81 -> 8.8263357 | H81: 8.2 | I81: =(G81/H81-1) -> 0.076382405 | J81: 0.196 | K81: 1.76 | L81: =F81/D81 -> 1.3278443 | M81: 0.5 | N81: =M81*L81 -> 0.66392217 | O81: =N81/P81 -> 0.05664865 | P81: =IFERROR(__xludf.DUMMYFUNCTION("GOOGLEFINANCE(""BVMF:CMIG4"")"),11.72) -> 11.72 | Q81: 10.65 | R81: =1-(P81/Q81) -> -0.10046948 | S81: 5x por ano | T81: mar abr jun set dez | U81: 46091
A82: Unipar | B82: UNIP6 | C82: Químicos | D82: 112722576 | E82: =D82*P82 -> 7464488983 | F82: 550000000 | G82: =P82/L82 -> 13.571798 | H82: 9.3 | I82: =(G82/H82-1) -> 0.45933313 | J82: 0.165 | K82: 0.89 | L82: =F82/D82 -> 4.8792355 | M82: 0.95 | N82: =M82*L82 -> 4.6352738 | O82: =N82/P82 -> 0.069998094 | P82: =IFERROR(__xludf.DUMMYFUNCTION("GOOGLEFINANCE(""BVMF:UNIP6"")"),66.22) -> 66.22 | Q82: 60 | R82: =1-(P82/Q82) -> -0.10366667 | S82: Semestral | T82: março e dezembro | U82: 46091
A83: Sanepar | B83: SAPR3 | C83: Saneamento | D83: 1511205519 | E83: =D83*P83 -> 13343944733 | F83: 1700000000 | G83: =P83/L83 -> 7.8493793 | H83: 7 | I83: =(G83/H83-1) -> 0.12133989 | J83: 0.178 | K83: 1.7 | L83: =F83/D83 -> 1.1249297 | M83: 0.3185 | N83: =M83*L83 -> 0.35829012 | O83: =N83/P83 -> 0.040576457 | P83: =IFERROR(__xludf.DUMMYFUNCTION("GOOGLEFINANCE(""BVMF:SAPR3"")"),8.83) -> 8.83 | Q83: 8 | R83: =1-(P83/Q83) -> -0.10375 | S83: Semestral | T83: jun e dez | U83: 46091
A84: ISA Energia | B84: ISAE4 | C84: Energia | D84: 658883304 | E84: =D84*P84 -> 18237889855 | F84: 1400000000 | G84: =P84/L84 -> 13.027064 | H84: 7.8 | I84: =(G84/H84-1) -> 0.67013643 | J84: -0.005 | K84: 3.16 | L84: =F84/D84 -> 2.1248072 | M84: 0.75 | N84: =M84*L84 -> 1.5936054 | O84: =N84/P84 -> 0.05757245 | P84: =IFERROR(__xludf.DUMMYFUNCTION("GOOGLEFINANCE(""BVMF:ISAE4"")"),27.68) -> 27.68 | Q84: 24 | R84: =1-(P84/Q84) -> -0.15333333 | S84: Anual | T84: dezembro | U84: 46091
A85: CEB | B85: CEBR3 | C85: Energia | D85: 72082000 | E85: =D85*P85 -> 2248958400 | F85: 200000000 | G85: =P85/L85 -> 11.244792 | H85: 7.1 | I85: =(G85/H85-1) -> 0.58377352 | J85: 0.073 | K85: -3.17 | L85: =F85/D85 -> 2.7746178 | M85: 0.778 | N85: =M85*L85 -> 2.1586526 | O85: =N85/P85 -> 0.069187585 | P85: =IFERROR(__xludf.DUMMYFUNCTION("GOOGLEFINANCE(""BVMF:CEBR3"")"),31.2) -> 31.2 | Q85: =N85/0.08 -> 26.983158 | R85: =1-(P85/Q85) -> -0.15627681 | S85: Semestral | T85: Abril e novembro | U85: 46091
A86: Electro Aço Altona | B86: EALT4 | C86: Industrial | D86: 22500000 | E86: =D86*P86 -> 319050000 | F86: 60000000 | G86: =P86/L86 -> 5.3175 | H86: 6.8 | I86: =(G86/H86-1) -> -0.21801471 | J86: 0.303 | K86: 0.77 | L86: =F86/D86 -> 2.6666667 | M86: 0.3 | N86: =M86*L86 -> 0.8 | O86: =N86/P86 -> 0.056417489 | P86: =IFERROR(__xludf.DUMMYFUNCTION("GOOGLEFINANCE(""BVMF:EALT4"")"),14.18) -> 14.18 | Q86: =4.5*L86 -> 12 | R86: =1-(P86/Q86) -> -0.18166667 | S86: Quadrimestral | T86: abril, junho e dezembro | U86: 46091
A87: Copel | B87: CPLE3 | C87: Energia | D87: 2969288600 | E87: =D87*P87 -> 41837276374 | F87: 2700000000 | G87: =P87/L87 -> 15.495288 | H87: 8.8 | I87: =(G87/H87-1) -> 0.76082813 | J87: -0.05 | K87: 2.3 | L87: =F87/D87 -> 0.90930871 | M87: 0.95 | N87: =M87*L87 -> 0.86384328 | O87: =N87/P87 -> 0.061308962 | P87: =IFERROR(__xludf.DUMMYFUNCTION("GOOGLEFINANCE(""BVMF:CPLE3"")"),14.09) -> 14.09 | Q87: =N87/0.075 -> 11.51791 | R87: =1-(P87/Q87) -> -0.22331217 | S87: Semestral | T87: abril e dez | U87: 46091
A88: Copasa | B88: CSMG3 | C88: Saneamento | D88: 379181000 | E88: =D88*P88 -> 19743954670 | F88: 1500000000 | G88: =P88/L88 -> 13.162636 | H88: 9.1 | I88: =(G88/H88-1) -> 0.44644357 | J88: 0.107 | K88: 2.3 | L88: =F88/D88 -> 3.9558944 | M88: 0.5 | N88: =M88*L88 -> 1.9779472 | O88: =N88/P88 -> 0.037986311 | P88: =IFERROR(__xludf.DUMMYFUNCTION("GOOGLEFINANCE(""BVMF:CSMG3"")"),52.07) -> 52.07 | Q88: 42 | R88: =1-(P88/Q88) -> -0.2397619 | S88: Trimestral | T88: mar, jun, set e dez | U88: 46091
A89: Engie Brasil | B89: EGIE3 | C89: Energia | D89: 1142298836 | E89: =D89*P89 -> 36039528276 | F89: 3100000000 | G89: =P89/L89 -> 11.625654 | H89: 13.8 | I89: =(G89/H89-1) -> -0.15756128 | J89: 0.0235 | K89: 2.9 | L89: =F89/D89 -> 2.7138258 | M89: 0.55 | N89: =M89*L89 -> 1.4926042 | O89: =N89/P89 -> 0.047309165 | P89: =IFERROR(__xludf.DUMMYFUNCTION("GOOGLEFINANCE(""BVMF:EGIE3"")"),31.55) -> 31.55 | Q89: =N89/0.06 -> 24.876736 | R89: =1-(P89/Q89) -> -0.26825319 | S89: Quadrimestral | T89: maio, ago e dez | U89: 46091
A90: Telefonica Vivo | B90: VIVT3 | C90: Telecomunicações | D90: 3195609730 | E90: =D90*P90 -> 129869579427 | F90: 7000000000 | G90: =P90/L90 -> 18.552797 | H90: 15.5 | I90: =(G90/H90-1) -> 0.19695465 | J90: 0.041 | K90: 0.4 | L90: =F90/D90 -> 2.1905053 | M90: 1 | N90: =M90*L90 -> 2.1905053 | O90: =N90/P90 -> 0.053900228 | P90: =IFERROR(__xludf.DUMMYFUNCTION("GOOGLEFINANCE(""BVMF:VIVT3"")"),40.64) -> 40.64 | Q90: =N90/0.07 -> 31.292933 | R90: =1-(P90/Q90) -> -0.29869579 | S90: 6x por ano | T90: fev até dez | U90: 46091
A91: Ambev | B91: ABEV3 | C91: Bebidas | D91: 15727892789 | E91: =D91*P91 -> 235918391835 | F91: 15300000000 | G91: =P91/L91 -> 15.419503 | H91: 22 | I91: =(G91/H91-1) -> -0.29911351 | J91: 0.053 | K91: -0.57 | L91: =F91/D91 -> 0.97279402 | M91: 0.9 | N91: =M91*L91 -> 0.87551462 | O91: =N91/P91 -> 0.058367641 | P91: =IFERROR(__xludf.DUMMYFUNCTION("GOOGLEFINANCE(""BVMF:ABEV3"")"),15.0) -> 15 | Q91: 11.5 | R91: =1-(P91/Q91) -> -0.30434783 | S91: Anual | T91: dezembro | U91: 46091
A92: Energisa | B92: ENGI4 | C92: Energia | D92: 2517311233 | E92: =D92*P92 -> 25072419881 | F92: 2300000000 | G92: =P92/L92 -> 10.901052 | H92: 9.2 | I92: =(G92/H92-1) -> 0.18489697 | J92: 0.069 | K92: 3.6 | L92: =F92/D92 -> 0.91367328 | M92: 0.5 | N92: =M92*L92 -> 0.45683664 | O92: =N92/P92 -> 0.045867132 | P92: =IFERROR(__xludf.DUMMYFUNCTION("GOOGLEFINANCE(""BVMF:ENGI4"")"),9.96) -> 9.96 | Q92: =N92/0.06 -> 7.613944 | R92: =1-(P92/Q92) -> -0.30812625 | S92: Quadrimestral | T92: mar, ago e nov | U92: 46091
A93: Vibra Energia | B93: VBBR3 | C93: Oléo, gás e biocomb. | D93: 1114510920 | E93: =D93*P93 -> 32755475939 | F93: 2600000000 | G93: =P93/L93 -> 12.59826 | H93: 9 | I93: =(G93/H93-1) -> 0.39980666 | J93: 0.075 | K93: 2.22 | L93: =F93/D93 -> 2.3328618 | M93: 0.5 | N93: =M93*L93 -> 1.1664309 | O93: =N93/P93 -> 0.03968802 | P93: =IFERROR(__xludf.DUMMYFUNCTION("GOOGLEFINANCE(""BVMF:VBBR3"")"),29.39) -> 29.39 | Q93: 22 | R93: =1-(P93/Q93) -> -0.33590909 | S93: Quadrimestral | T93: abr set e dez | U93: 46091

Sheet Preço teto Bazin adaptado
A1: Vídeo da planilha: | B1: PLANILHA para os MEMBROS: QUAIS AS DIFERENÇAS? E FORMAS DE UTILIZAR
A3: Empresa | B3: Código | C3: Atuação | D3: Quantidade total de ações | E3: Valor de mercado | F3: Lucro líquido estimado | G3: P/L projetado | H3: P/L médio (últ. 10 anos) | I3: Desvio do P/L da sua média | J3: CAGR lucros (últ. 5 anos) | K3: Dívida líquida/EBITDA | L3: Lucro por ação estimado | M3: Payout esperado | N3: Dividendo por ação bruto projetado | O3: Dividend Yield bruto estimado | P3: Cotação atual | Q3: Preço Teto baseado em 7,55% de yield (Taxa do Tesouro IPCA+ 2037 com juros semestrais) | R3: Margem de segurança | S3: Frequência nos anúncios | T3: Meses que costumam anunciar dividendos | U3: Última atualização
A4: Allos | B4: ALOS3 | C4: Shoppings | D4: 499180780 | E4: =D4*P4 -> 14436308158 | F4: 1500000000 | G4: =P4/L4 -> 9.6242054 | H4: 14.4 | I4: =(G4/H4-1) -> -0.3316524 | J4: 0.365 | K4: 1.8 | L4: =F4/D4 -> 3.0049234 | M4: 1.158 | N4: =M4*L4 -> 3.4797013 | O4: =N4/P4 -> 0.12032162 | P4: =IFERROR(__xludf.DUMMYFUNCTION("GOOGLEFINANCE(""BVMF:ALOS3"")"),28.92) -> 28.92 | Q4: =N4/0.0755 -> 46.088759 | R4: =1-(P4/Q4) -> 0.3725151 | S4: Mensal | T4: jan-dez | U4: 46091
A5: Stone | B5: STOC34 | C5: Serviços Financeiros | D5: 248904657 | E5: =D5*P5 -> 18244711358 | F5: 2760000000 | G5: =P5/L5 -> 6.6104027 | H5: 21.4 | I5: =(G5/H5-1) -> -0.69110268 | J5: 0.1 | K5: 0 | L5: =F5/D5 -> 11.088583 | M5: 0.7 | N5: =M5*L5 -> 7.7620082 | O5: =N5/P5 -> 0.1058937 | P5: =IFERROR(__xludf.DUMMYFUNCTION("GOOGLEFINANCE(""BVMF:STOC34"")"),73.3) -> 73.3 | Q5: =N5/0.0755 -> 102.80806 | R5: =1-(P5/Q5) -> 0.28702086 | S5: Indefinido | T5: Indefinido | U5: 46094
A6: BB Seguridade | B6: BBSE3 | C6: Seguros | D6: 1941214909 | E6: =D6*P6 -> 68039582560 | F6: 8100000000 | G6: =P6/L6 -> 8.3999485 | H6: 12.1 | I6: =(G6/H6-1) -> -0.30578938 | J6: 0.183 | K6: 0 | L6: =F6/D6 -> 4.1726446 | M6: 0.88 | N6: =M6*L6 -> 3.6719273 | O6: =N6/P6 -> 0.10476255 | P6: =IFERROR(__xludf.DUMMYFUNCTION("GOOGLEFINANCE(""BVMF:BBSE3"")"),35.05) -> 35.05 | Q6: =N6/0.0755 -> 48.634799 | R6: =1-(P6/Q6) -> 0.2793226 | S6: Semestral | T6: fevereiro e agosto | U6: 46091
A7: Banco BMG | B7: BMGB4 | C7: Bancos | D7: 631845354 | E7: =D7*P7 -> 2988628524 | F7: 600000000 | G7: =P7/L7 -> 4.9810475 | H7: 8.3 | I7: =(G7/H7-1) -> -0.39987379 | J7: 0.0026 | K7: 0 | L7: =F7/D7 -> 0.94959945 | M7: 0.5 | N7: =M7*L7 -> 0.47479972 | O7: =N7/P7 -> 0.10038049 | P7: =IFERROR(__xludf.DUMMYFUNCTION("GOOGLEFINANCE(""BVMF:BMGB4"")"),4.73) -> 4.73 | Q7: =N7/0.0755 -> 6.2887381 | R7: =1-(P7/Q7) -> 0.24786182 | S7: Trimestral | T7: abr jul out e dez | U7: 46091
A8: JHSF | B8: JHSF3 | C8: Imobiliário | D8: 658316448 | E8: =D8*P8 -> 5661521453 | F8: 600000000 | G8: =P8/L8 -> 9.4358691 | H8: 5.4 | I8: =(G8/H8-1) -> 0.74738316 | J8: 0.1529 | K8: 1.86 | L8: =F8/D8 -> 0.91141578 | M8: 0.9 | N8: =M8*L8 -> 0.8202742 | O8: =N8/P8 -> 0.095380721 | P8: =IFERROR(__xludf.DUMMYFUNCTION("GOOGLEFINANCE(""BVMF:JHSF3"")"),8.6) -> 8.6 | Q8: =N8/0.0755 -> 10.864559 | R8: =1-(P8/Q8) -> 0.20843543 | S8: Mensal | T8: jan a dezembro | U8: 46091
A9: Marcopolo | B9: POMO3 | C9: Industrial | D9: 1241439543 | E9: =D9*P9 -> 6852746277 | F9: 1300000000 | G9: =P9/L9 -> 5.2713433 | H9: 10.8 | I9: =(G9/H9-1) -> -0.51191266 | J9: 0.682 | K9: 0.85 | L9: =F9/D9 -> 1.0471714 | M9: 0.5 | N9: =M9*L9 -> 0.52358571 | O9: =N9/P9 -> 0.094852483 | P9: =IFERROR(__xludf.DUMMYFUNCTION("GOOGLEFINANCE(""BVMF:POMO3"")"),5.52) -> 5.52 | Q9: =N9/0.0755 -> 6.93491 | R9: =1-(P9/Q9) -> 0.20402716 | S9: Trimestral | T9: fev mai ago e nov | U9: 46091
A10: Banco Banrisul | B10: BRSR6 | C10: Bancos | D10: 408974000 | E10: =D10*P10 -> 6919840080 | F10: 1400000000 | G10: =P10/L10 -> 4.9427429 | H10: 6.5 | I10: =(G10/H10-1) -> -0.23957801 | J10: 0.011 | K10: 0 | L10: =F10/D10 -> 3.4232005 | M10: 0.45 | N10: =M10*L10 -> 1.5404402 | O10: =N10/P10 -> 0.091042566 | P10: =IFERROR(__xludf.DUMMYFUNCTION("GOOGLEFINANCE(""BVMF:BRSR6"")"),16.92) -> 16.92 | Q10: =N10/0.0755 -> 20.403182 | R10: =1-(P10/Q10) -> 0.17071758 | S10: Trimestral | T10: Mar, jun, set, dez | U10: 46091
A11: Marcopolo | B11: POMO4 | C11: Industrial | D11: 1241439543 | E11: =D11*P11 -> 7312078908 | F11: 1300000000 | G11: =P11/L11 -> 5.6246761 | H11: 9.7 | I11: =(G11/H11-1) -> -0.42013649 | J11: 0.682 | K11: 0.85 | L11: =F11/D11 -> 1.0471714 | M11: 0.5 | N11: =M11*L11 -> 0.52358571 | O11: =N11/P11 -> 0.088894008 | P11: =IFERROR(__xludf.DUMMYFUNCTION("GOOGLEFINANCE(""BVMF:POMO4"")"),5.89) -> 5.89 | Q11: =N11/0.0755 -> 6.93491 | R11: =1-(P11/Q11) -> 0.15067391 | S11: Trimestral | T11: fev mai ago e nov | U11: 46091
A12: Mahle Metal Leve | B12: LEVE3 | C12: Automóveis e Motocicletas | D12: 135539000 | E12: =D12*P12 -> 4667963160 | F12: 630000000 | G12: =P12/L12 -> 7.4094653 | H12: 11.2 | I12: =(G12/H12-1) -> -0.3384406 | J12: 0.345 | K12: 0.87 | L12: =F12/D12 -> 4.6481087 | M12: 0.65 | N12: =M12*L12 -> 3.0212706 | O12: =N12/P12 -> 0.087725628 | P12: =IFERROR(__xludf.DUMMYFUNCTION("GOOGLEFINANCE(""BVMF:LEVE3"")"),34.44) -> 34.44 | Q12: =N12/0.0755 -> 40.01683 | R12: =1-(P12/Q12) -> 0.1393621 | S12: Semestral | T12: abril e nov | U12: 46091
A13: Banco ABC Brasil | B13: ABCB4 | C13: Bancos | D13: 244657000 | E13: =D13*P13 -> 6295024610 | F13: 1100000000 | G13: =P13/L13 -> 5.7227496 | H13: 6.7 | I13: =(G13/H13-1) -> -0.14585826 | J13: 0.275 | K13: 0 | L13: =F13/D13 -> 4.4960904 | M13: 0.5 | N13: =M13*L13 -> 2.2480452 | O13: =N13/P13 -> 0.087370588 | P13: =IFERROR(__xludf.DUMMYFUNCTION("GOOGLEFINANCE(""BVMF:ABCB4"")"),25.73) -> 25.73 | Q13: =N13/0.0755 -> 29.775433 | R13: =1-(P13/Q13) -> 0.1358648 | S13: Semestral | T13: junho e dez | U13: 46091
A14: Mdias Branco | B14: MDIA3 | C14: Alimentos | D14: 335383253 | E14: =D14*P14 -> 7354954738 | F14: 800000000 | G14: =P14/L14 -> 9.1936934 | H14: 17.5 | I14: =(G14/H14-1) -> -0.47464609 | J14: 0.055 | K14: -0.5 | L14: =F14/D14 -> 2.3853308 | M14: 0.8 | N14: =M14*L14 -> 1.9082646 | O14: =N14/P14 -> 0.087016171 | P14: =IFERROR(__xludf.DUMMYFUNCTION("GOOGLEFINANCE(""BVMF:MDIA3"")"),21.93) -> 21.93 | Q14: =N14/0.0755 -> 25.275028 | R14: =1-(P14/Q14) -> 0.13234518 | S14: Mensal | T14: jan a dezembro | U14: 46091
A15: Pagbank | B15: PAGS34 | C15: Bancos | D15: =279705823*5 -> 1398529115 | E15: =D15*P15 -> 13831452947 | F15: 2550000000 | G15: =P15/L15 -> 5.4240992 | H15: 21.4 | I15: =(G15/H15-1) -> -0.74653742 | J15: 0.158 | K15: 0 | L15: =F15/D15 -> 1.8233442 | M15: 0.4714 | N15: =M15*L15 -> 0.85952447 | O15: =N15/P15 -> 0.08690844 | P15: =IFERROR(__xludf.DUMMYFUNCTION("GOOGLEFINANCE(""BVMF:PAGS34"")"),9.89) -> 9.89 | Q15: =N15/0.0755 -> 11.38443 | R15: =1-(P15/Q15) -> 0.13126965 | S15: Trimestral | T15: fev jun set e dez | U15: 46091
A16: Bradespar | B16: BRAP4 | C16: Holding | D16: 393097000 | E16: =D16*P16 -> 8687443700 | F16: 1670000000 | G16: =P16/L16 -> 5.2020621 | H16: 8.7 | I16: =(G16/H16-1) -> -0.40206183 | J16: -0.059 | K16: -0.64 | L16: =F16/D16 -> 4.2483153 | M16: 0.45 | N16: =M16*L16 -> 1.9117419 | O16: =N16/P16 -> 0.086504158 | P16: =IFERROR(__xludf.DUMMYFUNCTION("GOOGLEFINANCE(""BVMF:BRAP4"")"),22.1) -> 22.1 | Q16: =N16/0.0755 -> 25.321085 | R16: =1-(P16/Q16) -> 0.12720958 | S16: Semestral | T16: abril e novembro | U16: 46091
A17: BR Partners | B17: BRBI11 | C17: Serviços Financeiros | D17: =314987000/3 -> 1.0499567e+08 | E17: =D17*P17 -> 1974968490 | F17: 210000000 | G17: =P17/L17 -> 9.4046119 | H17: 9.1 | I17: =(G17/H17-1) -> 0.03347383 | J17: 0.2 | K17: 0 | L17: =F17/D17 -> 2.0000825 | M17: 0.8 | N17: =M17*L17 -> 1.600066 | O17: =N17/P17 -> 0.085064648 | P17: =IFERROR(__xludf.DUMMYFUNCTION("GOOGLEFINANCE(""BVMF:BRBI11"")"),18.81) -> 18.81 | Q17: =N17/0.0755 -> 21.192928 | R17: =1-(P17/Q17) -> 0.11243976 | S17: Trimestral | T17: mar maio ago e nov | U17: 46091
A18: Tegma | B18: TGMA3 | C18: Logistica | D18: 66003000 | E18: =D18*P18 -> 2075794350 | F18: 220000000 | G18: =P18/L18 -> 9.4354289 | H18: 12.9 | I18: =(G18/H18-1) -> -0.26857141 | J18: 0.307 | K18: -0.35 | L18: =F18/D18 -> 3.3331818 | M18: 0.8 | N18: =M18*L18 -> 2.6665455 | O18: =N18/P18 -> 0.084786819 | P18: =IFERROR(__xludf.DUMMYFUNCTION("GOOGLEFINANCE(""BVMF:TGMA3"")"),31.45) -> 31.45 | Q18: =N18/0.0755 -> 35.318483 | R18: =1-(P18/Q18) -> 0.1095314 | S18: Quadrimestral | T18: abr ago e nov | U18: 46091
A19: Taesa | B19: TAEE3 | C19: Energia | D19: 1033496721 | E19: =D19*P19 -> 14313929586 | F19: 1270000000 | G19: =P19/L19 -> 11.270811 | H19: 8.6 | I19: =(G19/H19-1) -> 0.31055938 | J19: -0.058 | K19: 4.1 | L19: =F19/D19 -> 1.228838 | M19: 0.95 | N19: =M19*L19 -> 1.1673961 | O19: =N19/P19 -> 0.084288524 | P19: =IFERROR(__xludf.DUMMYFUNCTION("GOOGLEFINANCE(""BVMF:TAEE3"")"),13.85) -> 13.85 | Q19: =N19/0.0755 -> 15.462199 | R19: =1-(P19/Q19) -> 0.10426715 | S19: Trimestral | T19: mai, ago, nov, dez | U19: 46091
A20: Tim | B20: TIMS3 | C20: Telecomunicações | D20: 2420598680 | E20: =D20*P20 -> 64387924888 | F20: 5400000000 | G20: =P20/L20 -> 11.92369 | H20: 14.8 | I20: =(G20/H20-1) -> -0.19434528 | J20: 0.145 | K20: -0.18 | L20: =F20/D20 -> 2.2308531 | M20: 1 | N20: =M20*L20 -> 2.2308531 | O20: =N20/P20 -> 0.083866657 | P20: =IFERROR(__xludf.DUMMYFUNCTION("GOOGLEFINANCE(""BVMF:TIMS3"")"),26.6) -> 26.6 | Q20: =N20/0.0755 -> 29.547723 | R20: =1-(P20/Q20) -> 0.099761421 | S20: 5x por ano | T20: mar abr jun set dez | U20: 46091
A21: Banco Banese | B21: BGIP4 | C21: Bancos | D21: 21548228 | E21: =D21*P21 -> 8.1085982e+08 | F21: 150000000 | G21: =P21/L21 -> 5.4057321 | H21: 7.3 | I21: =(G21/H21-1) -> -0.25948875 | J21: 0.22 | K21: 0 | L21: =F21/D21 -> 6.9611292 | M21: 0.45 | N21: =M21*L21 -> 3.1325082 | O21: =N21/P21 -> 0.083244968 | P21: =IFERROR(__xludf.DUMMYFUNCTION("GOOGLEFINANCE(""BVMF:BGIP4"")"),37.63) -> 37.63 | Q21: =N21/0.0755 -> 41.490174 | R21: =1-(P21/Q21) -> 0.093038276 | S21: Trimestral | T21: fev maio ago e nov | U21: 46091
A22: Taesa | B22: TAEE11 | C22: Energia | D22: =1033496721/3 -> 344498907 | E22: =D22*P22 -> 14537853875 | F22: 1270000000 | G22: =P22/L22 -> 11.447129 | H22: 8.6 | I22: =(G22/H22-1) -> 0.33106152 | J22: -0.058 | K22: 4.1 | L22: =F22/D22 -> 3.6865139 | M22: 0.95 | N22: =M22*L22 -> 3.5021882 | O22: =N22/P22 -> 0.082990241 | P22: =IFERROR(__xludf.DUMMYFUNCTION("GOOGLEFINANCE(""BVMF:TAEE11"")"),42.2) -> 42.2 | Q22: =N22/0.0755 -> 46.386598 | R22: =1-(P22/Q22) -> 0.090254482 | S22: Trimestral | T22: mai, ago, nov, dez | U22: 46091
A23: Log | B23: LOGG3 | C23: Exploração de imóveis | D23: 86999140 | E23: =D23*P23 -> 2289817365 | F23: 300000000 | G23: =P23/L23 -> 7.6327245 | H23: 8.6 | I23: =(G23/H23-1) -> -0.11247389 | J23: 0.2197 | K23: 0.7 | L23: =F23/D23 -> 3.4483099 | M23: 0.63 | N23: =M23*L23 -> 2.1724353 | O23: =N23/P23 -> 0.082539334 | P23: =IFERROR(__xludf.DUMMYFUNCTION("GOOGLEFINANCE(""BVMF:LOGG3"")"),26.32) -> 26.32 | Q23: =N23/0.0755 -> 28.773977 | R23: =1-(P23/Q23) -> 0.085284598 | S23: Trimestral | T23: fev maio ago e nov | U23: 46091
A24: Taesa | B24: TAEE4 | C24: Energia | D24: 1033496721 | E24: =D24*P24 -> 14644648537 | F24: 1270000000 | G24: =P24/L24 -> 11.531219 | H24: 8.6 | I24: =(G24/H24-1) -> 0.34083946 | J24: -0.058 | K24: 4.1 | L24: =F24/D24 -> 1.228838 | M24: 0.95 | N24: =M24*L24 -> 1.1673961 | O24: =N24/P24 -> 0.082385043 | P24: =IFERROR(__xludf.DUMMYFUNCTION("GOOGLEFINANCE(""BVMF:TAEE4"")"),14.17) -> 14.17 | Q24: =N24/0.0755 -> 15.462199 | R24: =1-(P24/Q24) -> 0.083571517 | S24: Trimestral | T24: mai, ago, nov, dez | U24: 46091
A25: Vale | B25: VALE3 | C25: Mineração | D25: 4437636744 | E25: =D25*P25 -> 347466957055 | F25: 53000000000 | G25: =P25/L25 -> 6.5559803 | H25: 10.3 | I25: =(G25/H25-1) -> -0.36349706 | J25: 0.023 | K25: 0.99 | L25: =F25/D25 -> 11.943294 | M25: 0.53 | N25: =M25*L25 -> 6.3299458 | O25: =N25/P25 -> 0.080842219 | P25: =IFERROR(__xludf.DUMMYFUNCTION("GOOGLEFINANCE(""BVMF:VALE3"")"),78.3) -> 78.3 | Q25: =N25/0.0755 -> 83.840342 | R25: =1-(P25/Q25) -> 0.066082049 | S25: Quadrimestral | T25: mar, ago e dez | U25: 46091
A26: Grendene | B26: GRND3 | C26: Calçados | D26: 902160000 | E26: =D26*P26 -> 4095806400 | F26: 600000000 | G26: =P26/L26 -> 6.826344 | H26: 10.9 | I26: =(G26/H26-1) -> -0.37372991 | J26: 0.149 | K26: -2.38 | L26: =F26/D26 -> 0.6650705 | M26: 0.55 | N26: =M26*L26 -> 0.36578877 | O26: =N26/P26 -> 0.080570214 | P26: =IFERROR(__xludf.DUMMYFUNCTION("GOOGLEFINANCE(""BVMF:GRND3"")"),4.54) -> 4.54 | Q26: =N26/0.0755 -> 4.8448844 | R26: =1-(P26/Q26) -> 0.062929142 | S26: Quadrimestral | T26: maio ago e nov | U26: 46091
A27: Banco Bradesco | B27: BBDC3 | C27: Bancos | D27: 10597012700 | E27: =D27*P27 -> 174002948534 | F27: 28000000000 | G27: =P27/L27 -> 6.214391 | H27: 9.2 | I27: =(G27/H27-1) -> -0.32452272 | J27: 0.0485 | K27: 0 | L27: =F27/D27 -> 2.6422541 | M27: 0.5 | N27: =M27*L27 -> 1.321127 | O27: =N27/P27 -> 0.080458407 | P27: =IFERROR(__xludf.DUMMYFUNCTION("GOOGLEFINANCE(""BVMF:BBDC3"")"),16.42) -> 16.42 | Q27: =N27/0.0755 -> 17.498371 | R27: =1-(P27/Q27) -> 0.061626956 | S27: Semestral | T27: junho e dez | U27: 46091
A28: Banco Itau | B28: ITUB3 | C28: Bancos | D28: 10753776126 | E28: =D28*P28 -> 441227434450 | F28: 50000000000 | G28: =P28/L28 -> 8.8245487 | H28: 9.1 | I28: =(G28/H28-1) -> -0.030269375 | J28: 0.238 | K28: 0 | L28: =F28/D28 -> 4.6495296 | M28: 0.7 | N28: =M28*L28 -> 3.2546707 | O28: =N28/P28 -> 0.07932417 | P28: =IFERROR(__xludf.DUMMYFUNCTION("GOOGLEFINANCE(""BVMF:ITUB3"")"),41.03) -> 41.03 | Q28: =N28/0.0755 -> 43.108221 | R28: =1-(P28/Q28) -> 0.048209391 | S28: Semestral | T28: fevereiro e ago | U28: 46091
A29: Itausa | B29: ITSA4 | C29: Holding | D29: 11213700000 | E29: =D29*P29 -> 147572292000 | F29: 17900000000 | G29: =P29/L29 -> 8.2442621 | H29: 8.7 | I29: =(G29/H29-1) -> -0.052383664 | J29: 0.164 | K29: 0 | L29: =F29/D29 -> 1.5962617 | M29: 0.65 | N29: =M29*L29 -> 1.0375701 | O29: =N29/P29 -> 0.078842714 | P29: =IFERROR(__xludf.DUMMYFUNCTION("GOOGLEFINANCE(""BVMF:ITSA4"")"),13.16) -> 13.16 | Q29: =N29/0.0755 -> 13.742651 | R29: =1-(P29/Q29) -> 0.042397246 | S29: Semestral | T29: fevereiro e ago | U29: 46091
A30: Odontoprev | B30: ODPV3 | C30: Seguros | D30: 545092900 | E30: =D30*P30 -> 7195226280 | F30: 595000000 | G30: =P30/L30 -> 12.092817 | H30: 19.4 | I30: =(G30/H30-1) -> -0.3766589 | J30: 0.1 | K30: -0.64 | L30: =F30/D30 -> 1.0915571 | M30: 0.95 | N30: =M30*L30 -> 1.0369792 | O30: =N30/P30 -> 0.07855903 | P30: =IFERROR(__xludf.DUMMYFUNCTION("GOOGLEFINANCE(""BVMF:ODPV3"")"),13.2) -> 13.2 | Q30: =N30/0.0755 -> 13.734824 | R30: =1-(P30/Q30) -> 0.038939258 | S30: 8x por ano | T30: mar abr mai jun ago set nov dez | U30: 46091
A31: Banco Santander | B31: SANB3 | C31: Bancos | D31: 7470968456 | E31: =D31*P31 -> 111915107471 | F31: 17400000000 | G31: =P31/L31 -> 6.4319027 | H31: 10.2 | I31: =(G31/H31-1) -> -0.3694213 | J31: -0.015 | K31: 0 | L31: =F31/D31 -> 2.3290153 | M31: 0.5 | N31: =M31*L31 -> 1.1645077 | O31: =N31/P31 -> 0.077737494 | P31: =IFERROR(__xludf.DUMMYFUNCTION("GOOGLEFINANCE(""BVMF:SANB3"")"),14.98) -> 14.98 | Q31: =N31/0.0755 -> 15.423943 | R31: =1-(P31/Q31) -> 0.028782688 | S31: Trimestral | T31: fev, abr, julho e out | U31: 46091
A32: Caixa Seguridade | B32: CXSE3 | C32: Seguros | D32: 3000000000 | E32: =D32*P32 -> 54420000000 | F32: 4700000000 | G32: =P32/L32 -> 11.578723 | H32: 12.4 | I32: =(G32/H32-1) -> -0.066231984 | J32: 0.197 | K32: 0 | L32: =F32/D32 -> 1.5666667 | M32: 0.9 | N32: =M32*L32 -> 1.41 | O32: =N32/P32 -> 0.077728776 | P32: =IFERROR(__xludf.DUMMYFUNCTION("GOOGLEFINANCE(""BVMF:CXSE3"")"),18.14) -> 18.14 | Q32: =N32/0.0755 -> 18.675497 | R32: =1-(P32/Q32) -> 0.028673759 | S32: Trimestral | T32: jan, abr, ago e nov | U32: 46091
A33: CPFL Energia | B33: CPFE3 | C33: Energia | D33: 1152254440 | E33: =D33*P33 -> 55481051286 | F33: 5500000000 | G33: =P33/L33 -> 10.087464 | H33: 13 | I33: =(G33/H33-1) -> -0.22404124 | J33: 0.087 | K33: 2.07 | L33: =F33/D33 -> 4.7732513 | M33: 0.781 | N33: =M33*L33 -> 3.7279093 | O33: =N33/P33 -> 0.07742283 | P33: =IFERROR(__xludf.DUMMYFUNCTION("GOOGLEFINANCE(""BVMF:CPFE3"")"),48.15) -> 48.15 | Q33: =N33/0.0755 -> 49.376282 | R33: =1-(P33/Q33) -> 0.024835439 | S33: Semestral | T33: abril e agosto | U33: 46091
A34: Banco Santander | B34: SANB11 | C34: Bancos | D34: =7470968456/2 -> 3735484228 | E34: =D34*P34 -> 112886333370 | F34: 17400000000 | G34: =P34/L34 -> 6.4877203 | H34: 10.2 | I34: =(G34/H34-1) -> -0.36394899 | J34: -0.015 | K34: 0 | L34: =F34/D34 -> 4.6580306 | M34: 0.5 | N34: =M34*L34 -> 2.3290153 | O34: =N34/P34 -> 0.077068674 | P34: =IFERROR(__xludf.DUMMYFUNCTION("GOOGLEFINANCE(""BVMF:SANB11"")"),30.22) -> 30.22 | Q34: =N34/0.0755 -> 30.847885 | R34: =1-(P34/Q34) -> 0.020354233 | S34: Trimestral | T34: fev, abr, julho e out | U34: 46091
A35: Grazziotin | B35: CGRA4 | C35: Varejo | D35: 23601907 | E35: =D35*P35 -> 6.5282875e+08 | F35: 100000000 | G35: =P35/L35 -> 6.5282875 | H35: 7.3 | I35: =(G35/H35-1) -> -0.10571404 | J35: 0.078 | K35: -1.63 | L35: =F35/D35 -> 4.2369458 | M35: 0.5 | N35: =M35*L35 -> 2.1184729 | O35: =N35/P35 -> 0.076589764 | P35: =IFERROR(__xludf.DUMMYFUNCTION("GOOGLEFINANCE(""BVMF:CGRA4"")"),27.66) -> 27.66 | Q35: =N35/0.0755 -> 28.059244 | R35: =1-(P35/Q35) -> 0.014228591 | S35: Semestral | T35: jun e dez | U35: 46091
A36: CEB | B36: CEBR6 | C36: Energia | D36: 72082000 | E36: =D36*P36 -> 2235983640 | F36: 200000000 | G36: =P36/L36 -> 11.179918 | H36: 7.1 | I36: =(G36/H36-1) -> 0.57463637 | J36: 0.073 | K36: -3.17 | L36: =F36/D36 -> 2.7746178 | M36: 0.778 | N36: =M36*L36*1.1 -> 2.3745179 | O36: =N36/P36 -> 0.076547966 | P36: =IFERROR(__xludf.DUMMYFUNCTION("GOOGLEFINANCE(""BVMF:CEBR6"")"),31.02) -> 31.02 | Q36: =N36/0.0755 -> 31.450568 | R36: =1-(P36/Q36) -> 0.01369032 | S36: Semestral | T36: Abril e novembro | U36: 46091
A37: Banco Bradesco | B37: BBDC4 | C37: Bancos | D37: 10597012700 | E37: =D37*P37 -> 201237271173 | F37: 28000000000 | G37: =P37/L37 -> 7.1870454 | H37: 10.1 | I37: =(G37/H37-1) -> -0.28841135 | J37: 0.0118 | K37: 0 | L37: =F37/D37 -> 2.6422541 | M37: 0.55 | N37: =M37*L37 -> 1.4532397 | O37: =N37/P37 -> 0.076526579 | P37: =IFERROR(__xludf.DUMMYFUNCTION("GOOGLEFINANCE(""BVMF:BBDC4"")"),18.99) -> 18.99 | Q37: =N37/0.0755 -> 19.248209 | R37: =1-(P37/Q37) -> 0.013414677 | S37: Semestral | T37: junho e dez | U37: 46091
A38: Banco Santander | B38: SANB4 | C38: Bancos | D38: 7470968456 | E38: =D38*P38 -> 114604656115 | F38: 17400000000 | G38: =P38/L38 -> 6.5864745 | H38: 10.2 | I38: =(G38/H38-1) -> -0.35426721 | J38: -0.015 | K38: 0 | L38: =F38/D38 -> 2.3290153 | M38: 0.5 | N38: =M38*L38 -> 1.1645077 | O38: =N38/P38 -> 0.075913146 | P38: =IFERROR(__xludf.DUMMYFUNCTION("GOOGLEFINANCE(""BVMF:SANB4"")"),15.34) -> 15.34 | Q38: =N38/0.0755 -> 15.423943 | R38: =1-(P38/Q38) -> 0.0054423521 | S38: Trimestral | T38: fev, abr, julho e out | U38: 46091
A39: CSU | B39: CSUD3 | C39: Tecnologia | D39: 41280684 | E39: =D39*P39 -> 7.5956459e+08 | F39: 115000000 | G39: =P39/L39 -> 6.6049094 | H39: 10.1 | I39: =(G39/H39-1) -> -0.34604857 | J39: 0.147 | K39: -0.13 | L39: =F39/D39 -> 2.7858066 | M39: 0.5 | N39: =M39*L39 -> 1.3929033 | O39: =N39/P39 -> 0.075701265 | P39: =IFERROR(__xludf.DUMMYFUNCTION("GOOGLEFINANCE(""BVMF:CSUD3"")"),18.4) -> 18.4 | Q39: =N39/0.0755 -> 18.44905 | R39: =1-(P39/Q39) -> 0.0026586746 | S39: Trimestral | T39: mar abr jun set e dez | U39: 46091
A40: Irani | B40: RANI3 | C40: Papel e Celulose | D40: 221172300 | E40: =D40*P40 -> 2012667930 | F40: 215000000 | G40: =P40/L40 -> 9.3612462 | H40: 9.4 | I40: =(G40/H40-1) -> -0.0041227462 | J40: 0.33 | K40: 2.06 | L40: =F40/D40 -> 0.9720928 | M40: 0.7 | N40: =M40*L40 -> 0.68046496 | O40: =N40/P40 -> 0.074776369 | P40: =IFERROR(__xludf.DUMMYFUNCTION("GOOGLEFINANCE(""BVMF:RANI3"")"),9.1) -> 9.1 | Q40: =N40/0.0755 -> 9.0127809 | R40: =1-(P40/Q40) -> -0.0096772672 | S40: 5x por ano | T40: mar abr mai ago nov | U40: 46091
A41: CEB | B41: CEBR5 | C41: Energia | D41: 72082000 | E41: =D41*P41 -> 2100469480 | F41: 200000000 | G41: =P41/L41 -> 10.502347 | H41: 7.1 | I41: =(G41/H41-1) -> 0.47920386 | J41: 0.073 | K41: -3.17 | L41: =F41/D41 -> 2.7746178 | M41: 0.778 | N41: =M41*L41 -> 2.1586526 | O41: =N41/P41 -> 0.074078677 | P41: =IFERROR(__xludf.DUMMYFUNCTION("GOOGLEFINANCE(""BVMF:CEBR5"")"),29.14) -> 29.14 | Q41: =N41/0.0755 -> 28.591426 | R41: =1-(P41/Q41) -> -0.019186669 | S41: Semestral | T41: Abril e novembro | U41: 46091
A42: IRB | B42: IRBR3 | C42: Seguros | D42: 81843000 | E42: =D42*P42 -> 4529191620 | F42: 670000000 | G42: =P42/L42 -> 6.7599875 | H42: 15.8 | I42: =(G42/H42-1) -> -0.57215269 | J42: 0 | K42: 0 | L42: =F42/D42 -> 8.1864057 | M42: 0.5 | N42: =M42*L42 -> 4.0932028 | O42: =N42/P42 -> 0.073964634 | P42: =IFERROR(__xludf.DUMMYFUNCTION("GOOGLEFINANCE(""BVMF:IRBR3"")"),55.34) -> 55.34 | Q42: =N42/0.0755 -> 54.214607 | R42: =1-(P42/Q42) -> -0.020758111 | S42: Indefinido | T42: Indefinido | U42: 46091
A43: Comgás | B43: CGAS5 | C43: Oléo, gás e biocomb. | D43: 132521000 | E43: =D43*P43 -> 17466267800 | F43: 1600000000 | G43: =P43/L43 -> 10.916417 | H43: 11.4 | I43: =(G43/H43-1) -> -0.042419529 | J43: 0.0684 | K43: 1.93 | L43: =F43/D43 -> 12.073558 | M43: 0.8 | N43: =M43*L43 -> 9.6588465 | O43: =N43/P43 -> 0.073284116 | P43: =IFERROR(__xludf.DUMMYFUNCTION("GOOGLEFINANCE(""BVMF:CGAS5"")"),131.8) -> 131.8 | Q43: =N43/0.0755 -> 127.93174 | R43: =1-(P43/Q43) -> -0.03023689 | S43: Quadrimestral | T43: março, agosto e novembro | U43: 46091
A44: CSN Mineração | B44: CMIN3 | C44: Mineração | D44: 5432045700 | E44: =D44*P44 -> 26291101188 | F44: 2500000000 | G44: =P44/L44 -> 10.51644 | H44: 7.8 | I44: =(G44/H44-1) -> 0.3482616 | J44: -0.1125 | K44: -0.69 | L44: =F44/D44 -> 0.46023177 | M44: 0.75 | N44: =M44*L44 -> 0.34517383 | O44: =N44/P44 -> 0.071316906 | P44: =IFERROR(__xludf.DUMMYFUNCTION("GOOGLEFINANCE(""BVMF:CMIN3"")"),4.84) -> 4.84 | Q44: =N44/0.0755 -> 4.5718388 | R44: =1-(P44/Q44) -> -0.058655008 | S44: Quadrimestral | T44: abr jul dez | U44: 46091
A45: Banco Itau | B45: ITUB4 | C45: Bancos | D45: 10753776126 | E45: =D45*P45 -> 455960107742 | F45: 50000000000 | G45: =P45/L45 -> 9.1192022 | H45: 10 | I45: =(G45/H45-1) -> -0.088079785 | J45: 0.238 | K45: 0 | L45: =F45/D45 -> 4.6495296 | M45: 0.65 | N45: =M45*L45 -> 3.0221942 | O45: =N45/P45 -> 0.071278165 | P45: =IFERROR(__xludf.DUMMYFUNCTION("GOOGLEFINANCE(""BVMF:ITUB4"")"),42.4) -> 42.4 | Q45: =N45/0.0755 -> 40.029062 | R45: =1-(P45/Q45) -> -0.059230404 | S45: Semestral | T45: fevereiro e ago | U45: 46091
A46: Metalúrgica Gerdau | B46: GOAU3 | C46: Siderurgia e Metalurgia | D46: 1324908144 | E46: =D46*P46 -> 10453525256 | F46: 1230000000 | G46: =P46/L46 -> 8.498801 | H46: 8.9 | I46: =(G46/H46-1) -> -0.045078537 | J46: 0.067 | K46: 0.85 | L46: =F46/D46 -> 0.92836625 | M46: 0.6 | N46: =M46*L46 -> 0.55701975 | O46: =N46/P46 -> 0.070598194 | P46: =IFERROR(__xludf.DUMMYFUNCTION("GOOGLEFINANCE(""BVMF:GOAU3"")"),7.89) -> 7.89 | Q46: =N46/0.0755 -> 7.377745 | R46: =1-(P46/Q46) -> -0.069432462 | S46: Trimestral | T46: mar mai ago nov | U46: 46091
A47: Unipar | B47: UNIP6 | C47: Químicos | D47: 112722576 | E47: =D47*P47 -> 7464488983 | F47: 550000000 | G47: =P47/L47 -> 13.571798 | H47: 9.3 | I47: =(G47/H47-1) -> 0.45933313 | J47: 0.165 | K47: 0.89 | L47: =F47/D47 -> 4.8792355 | M47: 0.95 | N47: =M47*L47 -> 4.6352738 | O47: =N47/P47 -> 0.069998094 | P47: =IFERROR(__xludf.DUMMYFUNCTION("GOOGLEFINANCE(""BVMF:UNIP6"")"),66.22) -> 66.22 | Q47: =N47/0.0755 -> 61.394355 | R47: =1-(P47/Q47) -> -0.0786008 | S47: Semestral | T47: março e dezembro | U47: 46091
A48: Kepler Weber | B48: KEPL3 | C48: Agronegócio | D48: 173367390 | E48: =D48*P48 -> 1333195229 | F48: 155000000 | G48: =P48/L48 -> 8.6012595 | H48: 9.8 | I48: =(G48/H48-1) -> -0.12232045 | J48: 0.173 | K48: -0.19 | L48: =F48/D48 -> 0.8940551 | M48: 0.6 | N48: =M48*L48 -> 0.53643306 | O48: =N48/P48 -> 0.069757225 | P48: =IFERROR(__xludf.DUMMYFUNCTION("GOOGLEFINANCE(""BVMF:KEPL3"")"),7.69) -> 7.69 | Q48: =N48/0.0755 -> 7.1050737 | R48: =1-(P48/Q48) -> -0.082325159 | S48: Quadrimestral | T48: mar ago e out | U48: 46091
A49: Wiz | B49: WIZC3 | C49: Seguros | D49: 159907000 | E49: =D49*P49 -> 1434365790 | F49: 200000000 | G49: =P49/L49 -> 7.171829 | H49: 8.6 | I49: =(G49/H49-1) -> -0.1660664 | J49: 0.111 | K49: 0.7 | L49: =F49/D49 -> 1.250727 | M49: 0.5 | N49: =M49*L49 -> 0.62536349 | O49: =N49/P49 -> 0.069717223 | P49: =IFERROR(__xludf.DUMMYFUNCTION("GOOGLEFINANCE(""BVMF:WIZC3"")"),8.97) -> 8.97 | Q49: =N49/0.0755 -> 8.2829602 | R49: =1-(P49/Q49) -> -0.082946171 | S49: Anual | T49: abril | U49: 46091
A50: CEB | B50: CEBR3 | C50: Energia | D50: 72082000 | E50: =D50*P50 -> 2248958400 | F50: 200000000 | G50: =P50/L50 -> 11.244792 | H50: 7.1 | I50: =(G50/H50-1) -> 0.58377352 | J50: 0.073 | K50: -3.17 | L50: =F50/D50 -> 2.7746178 | M50: 0.778 | N50: =M50*L50 -> 2.1586526 | O50: =N50/P50 -> 0.069187585 | P50: =IFERROR(__xludf.DUMMYFUNCTION("GOOGLEFINANCE(""BVMF:CEBR3"")"),31.2) -> 31.2 | Q50: =N50/0.0755 -> 28.591426 | R50: =1-(P50/Q50) -> -0.091236242 | S50: Semestral | T50: Abril e novembro | U50: 46091
A51: Banestes | B51: BEES3 | C51: Bancos | D51: 347504000 | E51: =D51*P51 -> 2988534400 | F51: 450000000 | G51: =P51/L51 -> 6.6411876 | H51: 7.2 | I51: =(G51/H51-1) -> -0.07761284 | J51: 0.06 | K51: 0 | L51: =F51/D51 -> 1.2949491 | M51: 0.45 | N51: =M51*L51 -> 0.58272711 | O51: =N51/P51 -> 0.067758966 | P51: =IFERROR(__xludf.DUMMYFUNCTION("GOOGLEFINANCE(""BVMF:BEES3"")"),8.6) -> 8.6 | Q51: =N51/0.0755 -> 7.7182398 | R51: =1-(P51/Q51) -> -0.11424369 | S51: Mensal | T51: jan-dez | U51: 46091
A52: Banco Pine | B52: PINE4 | C52: Bancos | D52: 258440362 | E52: =D52*P52 -> 2990154988 | F52: 450000000 | G52: =P52/L52 -> 6.6447889 | H52: 7.2 | I52: =(G52/H52-1) -> -0.077112658 | J52: 0.2986 | K52: 0 | L52: =F52/D52 -> 1.7412141 | M52: 0.45 | N52: =M52*L52 -> 0.78354634 | O52: =N52/P52 -> 0.067722242 | P52: =IFERROR(__xludf.DUMMYFUNCTION("GOOGLEFINANCE(""BVMF:PINE4"")"),11.57) -> 11.57 | Q52: =N52/0.0755 -> 10.378097 | R52: =1-(P52/Q52) -> -0.11484791 | S52: Trimestral | T52: jan, abr, jul, out | U52: 46091
A53: Dexxos | B53: DEXP3 | C53: Industrial | D53: 120961140 | E53: =D53*P53 -> 864872151 | F53: 130000000 | G53: =P53/L53 -> 6.6528627 | H53: 5.9 | I53: =(G53/H53-1) -> 0.12760385 | J53: 0.028 | K53: 0.08 | L53: =F53/D53 -> 1.0747253 | M53: 0.45 | N53: =M53*L53 -> 0.48362639 | O53: =N53/P53 -> 0.067640055 | P53: =IFERROR(__xludf.DUMMYFUNCTION("GOOGLEFINANCE(""BVMF:DEXP3"")"),7.15) -> 7.15 | Q53: =N53/0.0755 -> 6.4056476 | R53: =1-(P53/Q53) -> -0.11620252 | S53: Semestral | T53: abril e dezembro | U53: 46091
A54: Gerdau | B54: GGBR3 | C54: Siderurgia e Metalurgia | D54: 1989711987 | E54: =D54*P54 -> 31119095477 | F54: 3500000000 | G54: =P54/L54 -> 8.8911701 | H54: 10.5 | I54: =(G54/H54-1) -> -0.15322189 | J54: 0.067 | K54: 0.85 | L54: =F54/D54 -> 1.7590486 | M54: 0.6 | N54: =M54*L54 -> 1.0554291 | O54: =N54/P54 -> 0.067482681 | P54: =IFERROR(__xludf.DUMMYFUNCTION("GOOGLEFINANCE(""BVMF:GGBR3"")"),15.64) -> 15.64 | Q54: =N54/0.0755 -> 13.979194 | R54: =1-(P54/Q54) -> -0.11880558 | S54: Trimestral | T54: mar mai ago nov | U54: 46091
A55: Banco da Amazônia | B55: BAZA3 | C55: Bancos | D55: 56058000 | E55: =D55*P55 -> 4690372860 | F55: 900000000 | G55: =P55/L55 -> 5.2115254 | H55: 4.9 | I55: =(G55/H55-1) -> 0.063576612 | J55: 0.359 | K55: 0 | L55: =F55/D55 -> 16.0548 | M55: 0.35 | N55: =M55*L55 -> 5.6191801 | O55: =N55/P55 -> 0.06715884 | P55: =IFERROR(__xludf.DUMMYFUNCTION("GOOGLEFINANCE(""BVMF:BAZA3"")"),83.67) -> 83.67 | Q55: =N55/0.0755 -> 74.426227 | R55: =1-(P55/Q55) -> -0.12420048 | S55: Anual | T55: abril | U55: 46091
A56: B3 | B56: B3SA3 | C56: Serviços Financeiros | D56: 5168573066 | E56: =D56*P56 -> 87245513354 | F56: 5700000000 | G56: =P56/L56 -> 15.30623 | H56: 21 | I56: =(G56/H56-1) -> -0.27113189 | J56: 0.147 | K56: 0.05 | L56: =F56/D56 -> 1.1028189 | M56: 1 | N56: =M56*L56 -> 1.1028189 | O56: =N56/P56 -> 0.065332872 | P56: =IFERROR(__xludf.DUMMYFUNCTION("GOOGLEFINANCE(""BVMF:B3SA3"")"),16.88) -> 16.88 | Q56: =N56/0.0755 -> 14.606873 | R56: =1-(P56/Q56) -> -0.1556204 | S56: Trimestral | T56: mar jun set dez | U56: 46091
A57: Axia Energia | B57: AXIA3 | C57: Energia | D57: 2855268322 | E57: =D57*P57 -> 165605562676 | F57: 12000000000 | G57: =P57/L57 -> 13.800464 | H57: 9.3 | I57: =(G57/H57-1) -> 0.48392081 | J57: 0.0075 | K57: 1.8 | L57: =F57/D57 -> 4.2027574 | M57: 0.85 | N57: =M57*L57 -> 3.5723438 | O57: =N57/P57 -> 0.061592134 | P57: =IFERROR(__xludf.DUMMYFUNCTION("GOOGLEFINANCE(""BVMF:AXIA3"")"),58.0) -> 58 | Q57: =N57/0.0755 -> 47.315812 | R57: =1-(P57/Q57) -> -0.22580588 | S57: Semestral | T57: Abril e dezembro | U57: 46091
A58: Copel | B58: CPLE3 | C58: Energia | D58: 2969288600 | E58: =D58*P58 -> 41837276374 | F58: 2700000000 | G58: =P58/L58 -> 15.495288 | H58: 8.8 | I58: =(G58/H58-1) -> 0.76082813 | J58: -0.05 | K58: 2.3 | L58: =F58/D58 -> 0.90930871 | M58: 0.95 | N58: =M58*L58 -> 0.86384328 | O58: =N58/P58 -> 0.061308962 | P58: =IFERROR(__xludf.DUMMYFUNCTION("GOOGLEFINANCE(""BVMF:CPLE3"")"),14.09) -> 14.09 | Q58: =N58/0.0755 -> 11.441633 | R58: =1-(P58/Q58) -> -0.23146759 | S58: Semestral | T58: abril e dez | U58: 46091
A59: Romi | B59: ROMI3 | C59: Industrial | D59: 93171000 | E59: =D59*P59 -> 736050900 | F59: 90000000 | G59: =P59/L59 -> 8.1783433 | H59: 8.7 | I59: =(G59/H59-1) -> -0.059960536 | J59: -0.12 | K59: 3.04 | L59: =F59/D59 -> 0.9659658 | M59: 0.5 | N59: =M59*L59 -> 0.4829829 | O59: =N59/P59 -> 0.061137076 | P59: =IFERROR(__xludf.DUMMYFUNCTION("GOOGLEFINANCE(""BVMF:ROMI3"")"),7.9) -> 7.9 | Q59: =N59/0.0755 -> 6.3971245 | R59: =1-(P59/Q59) -> -0.23492984 | S59: Trimestral | T59: mar jun set e dez | U59: 46091
A60: Fleury | B60: FLRY3 | C60: Saúde | D60: 544279713 | E60: =D60*P60 -> 8376464783 | F60: 680000000 | G60: =P60/L60 -> 12.318331 | H60: 25 | I60: =(G60/H60-1) -> -0.50726678 | J60: 0.178 | K60: 1.51 | L60: =F60/D60 -> 1.2493576 | M60: 0.75 | N60: =M60*L60 -> 0.93701821 | O60: =N60/P60 -> 0.060884874 | P60: =IFERROR(__xludf.DUMMYFUNCTION("GOOGLEFINANCE(""BVMF:FLRY3"")"),15.39) -> 15.39 | Q60: =N60/0.0755 -> 12.410837 | R60: =1-(P60/Q60) -> -0.24004528 | S60: Semestral | T60: março e dezembro | U60: 46091
A61: Alupar | B61: ALUP11 | C61: Energia | D61: =914275704/3 -> 304758568 | E61: =D61*P61 -> 10508075425 | F61: 950000000 | G61: =P61/L61 -> 11.061132 | H61: 11.2 | I61: =(G61/H61-1) -> -0.012398926 | J61: -0.023 | K61: 3.5 | L61: =F61/D61 -> 3.1172216 | M61: 0.65 | N61: =M61*L61 -> 2.0261941 | O61: =N61/P61 -> 0.058764329 | P61: =IFERROR(__xludf.DUMMYFUNCTION("GOOGLEFINANCE(""BVMF:ALUP11"")"),34.48) -> 34.48 | Q61: =N61/0.0755 -> 26.837007 | R61: =1-(P61/Q61) -> -0.28479303 | S61: Trimestral | T61: abr mai ago nov | U61: 46091
A62: Petroreconcâvo | B62: RECV3 | C62: Oléo, gás e biocomb. | D62: 292973655 | E62: =D62*P62 -> 3761781730 | F62: 440000000 | G62: =P62/L62 -> 8.5495039 | H62: 9.3 | I62: =(G62/H62-1) -> -0.080698502 | J62: 0.3173 | K62: 1 | L62: =F62/D62 -> 1.5018415 | M62: 0.5 | N62: =M62*L62 -> 0.75092076 | O62: =N62/P62 -> 0.058482925 | P62: =IFERROR(__xludf.DUMMYFUNCTION("GOOGLEFINANCE(""BVMF:RECV3"")"),12.84) -> 12.84 | Q62: =N62/0.0755 -> 9.9459703 | R62: =1-(P62/Q62) -> -0.29097509 | S62: Semestral | T62: maio e dez | U62: 46091
A63: Vulcabras | B63: VULC3 | C63: Calçados | D63: 312632756 | E63: =D63*P63 -> 5130303526 | F63: 600000000 | G63: =P63/L63 -> 8.5505059 | H63: 9.5 | I63: =(G63/H63-1) -> -0.09994675 | J63: 0.795 | K63: 0.9 | L63: =F63/D63 -> 1.9191847 | M63: 0.5 | N63: =M63*L63 -> 0.95959235 | O63: =N63/P63 -> 0.058476072 | P63: =IFERROR(__xludf.DUMMYFUNCTION("GOOGLEFINANCE(""BVMF:VULC3"")"),16.41) -> 16.41 | Q63: =N63/0.0755 -> 12.709832 | R63: =1-(P63/Q63) -> -0.29112639 | S63: Mensal | T63: jan a dezembro | U63: 46091
A64: Ambev | B64: ABEV3 | C64: Bebidas | D64: 15727892789 | E64: =D64*P64 -> 235918391835 | F64: 15300000000 | G64: =P64/L64 -> 15.419503 | H64: 22 | I64: =(G64/H64-1) -> -0.29911351 | J64: 0.053 | K64: -0.57 | L64: =F64/D64 -> 0.97279402 | M64: 0.9 | N64: =M64*L64 -> 0.87551462 | O64: =N64/P64 -> 0.058367641 | P64: =IFERROR(__xludf.DUMMYFUNCTION("GOOGLEFINANCE(""BVMF:ABEV3"")"),15.0) -> 15 | Q64: =N64/0.0755 -> 11.59622 | R64: =1-(P64/Q64) -> -0.29352495 | S64: Anual | T64: dezembro | U64: 46091
A65: Porto Seguro | B65: PSSA3 | C65: Seguros | D65: 646586060 | E65: =D65*P65 -> 31883158619 | F65: 3700000000 | G65: =P65/L65 -> 8.6170699 | H65: 11 | I65: =(G65/H65-1) -> -0.21663001 | J65: 0.134 | K65: 0 | L65: =F65/D65 -> 5.7223628 | M65: 0.5 | N65: =M65*L65 -> 2.8611814 | O65: =N65/P65 -> 0.058024364 | P65: =IFERROR(__xludf.DUMMYFUNCTION("GOOGLEFINANCE(""BVMF:PSSA3"")"),49.31) -> 49.31 | Q65: =N65/0.0755 -> 37.896442 | R65: =1-(P65/Q65) -> -0.30117755 | S65: Quadrimestral | T65: mar, jun e out | U65: 46091
A66: ISA Energia | B66: ISAE4 | C66: Energia | D66: 658883304 | E66: =D66*P66 -> 18237889855 | F66: 1400000000 | G66: =P66/L66 -> 13.027064 | H66: 7.8 | I66: =(G66/H66-1) -> 0.67013643 | J66: -0.005 | K66: 3.16 | L66: =F66/D66 -> 2.1248072 | M66: 0.75 | N66: =M66*L66 -> 1.5936054 | O66: =N66/P66 -> 0.05757245 | P66: =IFERROR(__xludf.DUMMYFUNCTION("GOOGLEFINANCE(""BVMF:ISAE4"")"),27.68) -> 27.68 | Q66: =N66/0.0755 -> 21.107356 | R66: =1-(P66/Q66) -> -0.31139113 | S66: Anual | T66: dezembro | U66: 46091
A67: Petrobras | B67: PETR4 | C67: Oléo, gás e biocomb. | D67: 12888732761 | E67: =D67*P67 -> 575739692434 | F67: 73000000000 | G67: =P67/L67 -> 7.8868451 | H67: 6.2 | I67: =(G67/H67-1) -> 0.27207179 | J67: 0.656 | K67: 1.53 | L67: =F67/D67 -> 5.6638617 | M67: 0.45 | N67: =M67*L67 -> 2.5487378 | O67: =N67/P67 -> 0.057057035 | P67: =IFERROR(__xludf.DUMMYFUNCTION("GOOGLEFINANCE(""BVMF:PETR4"")"),44.67) -> 44.67 | Q67: =N67/0.0755 -> 33.758116 | R67: =1-(P67/Q67) -> -0.32323734 | S67: Trimestral | T67: abr mai ago nov | U67: 46091
A68: Cemig | B68: CMIG4 | C68: Energia | D68: 2861781207 | E68: =D68*P68 -> 33540075746 | F68: 3800000000 | G68: =P68/L68 -> 8.8263357 | H68: 8.2 | I68: =(G68/H68-1) -> 0.076382405 | J68: 0.196 | K68: 1.76 | L68: =F68/D68 -> 1.3278443 | M68: 0.5 | N68: =M68*L68 -> 0.66392217 | O68: =N68/P68 -> 0.05664865 | P68: =IFERROR(__xludf.DUMMYFUNCTION("GOOGLEFINANCE(""BVMF:CMIG4"")"),11.72) -> 11.72 | Q68: =N68/0.0755 -> 8.7936712 | R68: =1-(P68/Q68) -> -0.33277669 | S68: 5x por ano | T68: mar abr jun set dez | U68: 46091
A69: Electro Aço Altona | B69: EALT4 | C69: Industrial | D69: 22500000 | E69: =D69*P69 -> 319050000 | F69: 60000000 | G69: =P69/L69 -> 5.3175 | H69: 6.8 | I69: =(G69/H69-1) -> -0.21801471 | J69: 0.303 | K69: 0.77 | L69: =F69/D69 -> 2.6666667 | M69: 0.3 | N69: =M69*L69 -> 0.8 | O69: =N69/P69 -> 0.056417489 | P69: =IFERROR(__xludf.DUMMYFUNCTION("GOOGLEFINANCE(""BVMF:EALT4"")"),14.18) -> 14.18 | Q69: =N69/0.0755 -> 10.596026 | R69: =1-(P69/Q69) -> -0.3382375 | S69: Quadrimestral | T69: abril, junho e dezembro | U69: 46091
A70: Ferbasa | B70: FESA4 | C70: Siderurgia e Metalurgia | D70: 338867600 | E70: =D70*P70 -> 2511008916 | F70: 200000000 | G70: =P70/L70 -> 12.555045 | H70: 9.4 | I70: =(G70/H70-1) -> 0.33564304 | J70: 0.313 | K70: -1.33 | L70: =F70/D70 -> 0.59020101 | M70: 0.7 | N70: =M70*L70 -> 0.41314071 | O70: =N70/P70 -> 0.055754481 | P70: =IFERROR(__xludf.DUMMYFUNCTION("GOOGLEFINANCE(""BVMF:FESA4"")"),7.41) -> 7.41 | Q70: =N70/0.0755 -> 5.4720623 | R70: =1-(P70/Q70) -> -0.35415124 | S70: Quadrimestral | T70: jun set dez | U70: 46091
A71: Klabin | B71: KLBN11 | C71: Papel e Celulose | D71: 1248296000 | E71: =D71*P71 -> 23854936560 | F71: 8600000000 | G71: =P71/L71 -> 2.7738298 | H71: 9.6 | I71: =(G71/H71-1) -> -0.71105939 | J71: 0.1046 | K71: 3.7 | L71: =F71/D71 -> 6.8893916 | M71: 0.15 | N71: =M71*L71 -> 1.0334087 | O71: =N71/P71 -> 0.054076857 | P71: =IFERROR(__xludf.DUMMYFUNCTION("GOOGLEFINANCE(""BVMF:KLBN11"")"),19.11) -> 19.11 | Q71: =N71/0.0755 -> 13.687533 | R71: =1-(P71/Q71) -> -0.39616102 | S71: Trimestral | T71: fev, mai, ago, nov | U71: 46091
A72: Klabin | B72: KLBN4 | C72: Papel e Celulose | D72: 6241480000 | E72: =D72*P72 -> 23904868400 | F72: 8600000000 | G72: =P72/L72 -> 2.7796359 | H72: 9.6 | I72: =(G72/H72-1) -> -0.7104546 | J72: 0.1046 | K72: 3.7 | L72: =F72/D72 -> 1.3778783 | M72: 0.15 | N72: =M72*L72 -> 0.20668175 | O72: =N72/P72 -> 0.053963903 | P72: =IFERROR(__xludf.DUMMYFUNCTION("GOOGLEFINANCE(""BVMF:KLBN4"")"),3.83) -> 3.83 | Q72: =N72/0.0755 -> 2.7375066 | R72: =1-(P72/Q72) -> -0.39908338 | S72: Trimestral | T72: fev, mai, ago, nov | U72: 46091
A73: Klabin | B73: KLBN3 | C73: Papel e Celulose | D73: 6241480000 | E73: =D73*P73 -> 23967283200 | F73: 8600000000 | G73: =P73/L73 -> 2.7868934 | H73: 9.6 | I73: =(G73/H73-1) -> -0.7096986 | J73: 0.1046 | K73: 3.7 | L73: =F73/D73 -> 1.3778783 | M73: 0.15 | N73: =M73*L73 -> 0.20668175 | O73: =N73/P73 -> 0.053823372 | P73: =IFERROR(__xludf.DUMMYFUNCTION("GOOGLEFINANCE(""BVMF:KLBN3"")"),3.84) -> 3.84 | Q73: =N73/0.0755 -> 2.7375066 | R73: =1-(P73/Q73) -> -0.40273634 | S73: Trimestral | T73: fev, mai, ago, nov | U73: 46091
A74: Shulz | B74: SHUL4 | C74: Bens Industriais | D74: 356964439 | E74: =D74*P74 -> 1874063305 | F74: 200000000 | G74: =P74/L74 -> 9.3703165 | H74: 9.2 | I74: =(G74/H74-1) -> 0.018512666 | J74: 0.139 | K74: 0.12 | L74: =F74/D74 -> 0.5602799 | M74: 0.5 | N74: =M74*L74 -> 0.28013995 | O74: =N74/P74 -> 0.05335999 | P74: =IFERROR(__xludf.DUMMYFUNCTION("GOOGLEFINANCE(""BVMF:SHUL4"")"),5.25) -> 5.25 | Q74: =N74/0.0755 -> 3.7104629 | R74: =1-(P74/Q74) -> -0.4149178 | S74: Trimestral | T74: abr jun set dez | U74: 46091
A75: Celesc | B75: CLSC4 | C75: Energia | D75: 38572000 | E75: =D75*P75 -> 5583682720 | F75: 850000000 | G75: =P75/L75 -> 6.5690385 | H75: 5.6 | I75: =(G75/H75-1) -> 0.17304259 | J75: 0.073 | K75: 2.2 | L75: =F75/D75 -> 22.036711 | M75: 0.35 | N75: =M75*L75 -> 7.7128487 | O75: =N75/P75 -> 0.053280248 | P75: =IFERROR(__xludf.DUMMYFUNCTION("GOOGLEFINANCE(""BVMF:CLSC4"")"),144.76) -> 144.76 | Q75: =N75/0.0755 -> 102.15694 | R75: =1-(P75/Q75) -> -0.41703545 | S75: 5x por ano | T75: mar abr jun set dez | U75: 46091
A76: Telefonica Vivo | B76: VIVT3 | C76: Telecomunicações | D76: 3240086216 | E76: =D76*P76 -> 131677103818 | F76: 7000000000 | G76: =P76/L76 -> 18.811015 | H76: 15.5 | I76: =(G76/H76-1) -> 0.21361386 | J76: 0.041 | K76: 0.4 | L76: =F76/D76 -> 2.1604363 | M76: 1 | N76: =M76*L76 -> 2.1604363 | O76: =N76/P76 -> 0.053160343 | P76: =IFERROR(__xludf.DUMMYFUNCTION("GOOGLEFINANCE(""BVMF:VIVT3"")"),40.64) -> 40.64 | Q76: =N76/0.0755 -> 28.615051 | R76: =1-(P76/Q76) -> -0.42023162 | S76: 6x por ano | T76: fev até dez | U76: 46091
A77: Banco do Brasil | B77: BBAS3 | C77: Bancos | D77: 5708696148 | E77: =D77*P77 -> 135924055284 | F77: 24000000000 | G77: =P77/L77 -> 5.6635023 | H77: 6.4 | I77: =(G77/H77-1) -> -0.11507777 | J77: 0.132 | K77: 0 | L77: =F77/D77 -> 4.2041124 | M77: 0.3 | N77: =M77*L77 -> 1.2612337 | O77: =N77/P77 -> 0.052970756 | P77: =IFERROR(__xludf.DUMMYFUNCTION("GOOGLEFINANCE(""BVMF:BBAS3"")"),23.81) -> 23.81 | Q77: =N77/0.0755 -> 16.705082 | R77: =1-(P77/Q77) -> -0.42531475 | S77: 8x por ano | T77: mar jun set e dez | U77: 46091
A78: Multiplan | B78: MULT3 | C78: Shoppings | D78: 488678545 | E78: =D78*P78 -> 14621262066 | F78: 1500000000 | G78: =P78/L78 -> 9.747508 | H78: 16 | I78: =(G78/H78-1) -> -0.39078075 | J78: 0.018 | K78: 2.28 | L78: =F78/D78 -> 3.0695025 | M78: 0.5 | N78: =M78*L78 -> 1.5347512 | O78: =N78/P78 -> 0.051295162 | P78: =IFERROR(__xludf.DUMMYFUNCTION("GOOGLEFINANCE(""BVMF:MULT3"")"),29.92) -> 29.92 | Q78: =N78/0.0755 -> 20.327831 | R78: =1-(P78/Q78) -> -0.47187371 | S78: Quadrimestral | T78: jun set e dez | U78: 46091
A79: Sanepar | B79: SAPR4 | C79: Saneamento | D79: 1511205519 | E79: =D79*P79 -> 11681618662 | F79: 1700000000 | G79: =P79/L79 -> 6.8715404 | H79: 7 | I79: =(G79/H79-1) -> -0.018351373 | J79: 0.178 | K79: 1.7 | L79: =F79/D79 -> 1.1249297 | M79: 0.35 | N79: =M79*L79 -> 0.3937254 | O79: =N79/P79 -> 0.050934722 | P79: =IFERROR(__xludf.DUMMYFUNCTION("GOOGLEFINANCE(""BVMF:SAPR4"")"),7.73) -> 7.73 | Q79: =N79/0.0755 -> 5.214906 | R79: =1-(P79/Q79) -> -0.48228943 | S79: Semestral | T79: jun e dez | U79: 46091
A80: Emae | B80: EMAE4 | C80: Energia | D80: 36947000 | E80: =D80*P80 -> 1644141500 | F80: 200000000 | G80: =P80/L80 -> 8.2207075 | H80: 14.6 | I80: =(G80/H80-1) -> -0.43693784 | J80: 0 | K80: -12.04 | L80: =F80/D80 -> 5.4131594 | M80: 0.4 | N80: =M80*L80 -> 2.1652638 | O80: =N80/P80 -> 0.048657613 | P80: =IFERROR(__xludf.DUMMYFUNCTION("GOOGLEFINANCE(""BVMF:EMAE4"")"),44.5) -> 44.5 | Q80: =N80/0.0755 -> 28.67899 | R80: =1-(P80/Q80) -> -0.55165854 | S80: Anual | T80: abril | U80: 46091
A81: Engie Brasil | B81: EGIE3 | C81: Energia | D81: 1142298836 | E81: =D81*P81 -> 36039528276 | F81: 3100000000 | G81: =P81/L81 -> 11.625654 | H81: 13.8 | I81: =(G81/H81-1) -> -0.15756128 | J81: 0.0235 | K81: 2.9 | L81: =F81/D81 -> 2.7138258 | M81: 0.55 | N81: =M81*L81 -> 1.4926042 | O81: =N81/P81 -> 0.047309165 | P81: =IFERROR(__xludf.DUMMYFUNCTION("GOOGLEFINANCE(""BVMF:EGIE3"")"),31.55) -> 31.55 | Q81: =N81/0.0755 -> 19.769592 | R81: =1-(P81/Q81) -> -0.59588527 | S81: Quadrimestral | T81: maio, ago e dez | U81: 46091
A82: SLC Agrícola | B82: SLCE3 | C82: Agronegócio | D82: 496621582 | E82: =D82*P82 -> 8939188476 | F82: 840000000 | G82: =P82/L82 -> 10.641891 | H82: 10.8 | I82: =(G82/H82-1) -> -0.014639718 | J82: 0.084 | K82: 2.3 | L82: =F82/D82 -> 1.6914287 | M82: 0.5 | N82: =M82*L82 -> 0.84571435 | O82: =N82/P82 -> 0.046984131 | P82: =IFERROR(__xludf.DUMMYFUNCTION("GOOGLEFINANCE(""BVMF:SLCE3"")"),18.0) -> 18 | Q82: =N82/0.0755 -> 11.201515 | R82: =1-(P82/Q82) -> -0.60692555 | S82: Semestral | T82: abril e dezembro | U82: 46091
A83: Unifique | B83: FIQE3 | C83: Telecomunicações | D83: 399087000 | E83: =D83*P83 -> 2139106320 | F83: 200000000 | G83: =P83/L83 -> 10.695532 | H83: 9.7 | I83: =(G83/H83-1) -> 0.10263212 | J83: 0.2 | K83: 0.84 | L83: =F83/D83 -> 0.50114386 | M83: 0.5 | N83: =M83*L83 -> 0.25057193 | O83: =N83/P83 -> 0.046748494 | P83: =IFERROR(__xludf.DUMMYFUNCTION("GOOGLEFINANCE(""BVMF:FIQE3"")"),5.36) -> 5.36 | Q83: =N83/0.0755 -> 3.3188335 | R83: =1-(P83/Q83) -> -0.61502527 | S83: Quadrimestral | T83: fev junho e dez | U83: 46091
A84: Energisa | B84: ENGI4 | C84: Energia | D84: 2517311233 | E84: =D84*P84 -> 25072419881 | F84: 2300000000 | G84: =P84/L84 -> 10.901052 | H84: 9.2 | I84: =(G84/H84-1) -> 0.18489697 | J84: 0.069 | K84: 3.6 | L84: =F84/D84 -> 0.91367328 | M84: 0.5 | N84: =M84*L84 -> 0.45683664 | O84: =N84/P84 -> 0.045867132 | P84: =IFERROR(__xludf.DUMMYFUNCTION("GOOGLEFINANCE(""BVMF:ENGI4"")"),9.96) -> 9.96 | Q84: =N84/0.0755 -> 6.0508164 | R84: =1-(P84/Q84) -> -0.64605887 | S84: Quadrimestral | T84: mar, ago e nov | U84: 46091
A85: Suzano | B85: SUZB3 | C85: Papel e Celulose | D85: 1235911173 | E85: =D85*P85 -> 65997656638 | F85: 10000000000 | G85: =P85/L85 -> 6.5997657 | H85: 12.66 | I85: =(G85/H85-1) -> -0.4786915 | J85: 0.1094 | K85: 3.3 | L85: =F85/D85 -> 8.0911964 | M85: 0.3 | N85: =M85*L85 -> 2.4273589 | O85: =N85/P85 -> 0.045456159 | P85: =IFERROR(__xludf.DUMMYFUNCTION("GOOGLEFINANCE(""BVMF:SUZB3"")"),53.4) -> 53.4 | Q85: =N85/0.0755 -> 32.150449 | R85: =1-(P85/Q85) -> -0.66094103 | S85: Semestral | T85: abril e dez | U85: 46091
A86: Sanepar | B86: SAPR11 | C86: Saneamento | D86: =1511205519/5 -> 3.022411e+08 | E86: =D86*P86 -> 11929456367 | F86: 1700000000 | G86: =P86/L86 -> 7.0173273 | H86: 7 | I86: =(G86/H86-1) -> 0.002475325 | J86: 0.178 | K86: 1.7 | L86: =F86/D86 -> 5.6246486 | M86: 0.3 | N86: =M86*L86 -> 1.6873946 | O86: =N86/P86 -> 0.042751319 | P86: =IFERROR(__xludf.DUMMYFUNCTION("GOOGLEFINANCE(""BVMF:SAPR11"")"),39.47) -> 39.47 | Q86: =N86/0.0755 -> 22.349597 | R86: =1-(P86/Q86) -> -0.76602736 | S86: Semestral | T86: jun e dez | U86: 46091
A87: Banco Mercantil | B87: BMEB3 | C87: Bancos | D87: 123728626 | E87: =D87*P87 -> 8751325717 | F87: 1200000000 | G87: =P87/L87 -> 7.2927714 | H87: 6.2 | I87: =(G87/H87-1) -> 0.17625346 | J87: 0.301 | K87: 0 | L87: =F87/D87 -> 9.6986448 | M87: 0.3 | N87: =M87*L87 -> 2.9095935 | O87: =N87/P87 -> 0.041136625 | P87: =IFERROR(__xludf.DUMMYFUNCTION("GOOGLEFINANCE(""BVMF:BMEB3"")"),70.73) -> 70.73 | Q87: =N87/0.0755 -> 38.537662 | R87: =1-(P87/Q87) -> -0.83534748 | S87: Semestral | T87: fevereiro e ago | U87: 46091
A88: Sanepar | B88: SAPR3 | C88: Saneamento | D88: 1511205519 | E88: =D88*P88 -> 13343944733 | F88: 1700000000 | G88: =P88/L88 -> 7.8493793 | H88: 7 | I88: =(G88/H88-1) -> 0.12133989 | J88: 0.178 | K88: 1.7 | L88: =F88/D88 -> 1.1249297 | M88: 0.3185 | N88: =M88*L88 -> 0.35829012 | O88: =N88/P88 -> 0.040576457 | P88: =IFERROR(__xludf.DUMMYFUNCTION("GOOGLEFINANCE(""BVMF:SAPR3"")"),8.83) -> 8.83 | Q88: =N88/0.0755 -> 4.7455644 | R88: =1-(P88/Q88) -> -0.86068488 | S88: Semestral | T88: jun e dez | U88: 46091
A89: Vibra Energia | B89: VBBR3 | C89: Oléo, gás e biocomb. | D89: 1114510920 | E89: =D89*P89 -> 32755475939 | F89: 2600000000 | G89: =P89/L89 -> 12.59826 | H89: 9 | I89: =(G89/H89-1) -> 0.39980666 | J89: 0.075 | K89: 2.22 | L89: =F89/D89 -> 2.3328618 | M89: 0.5 | N89: =M89*L89 -> 1.1664309 | O89: =N89/P89 -> 0.03968802 | P89: =IFERROR(__xludf.DUMMYFUNCTION("GOOGLEFINANCE(""BVMF:VBBR3"")"),29.39) -> 29.39 | Q89: =N89/0.0755 -> 15.449416 | R89: =1-(P89/Q89) -> -0.90233726 | S89: Quadrimestral | T89: abr set e dez | U89: 46091
A90: Banco Mercantil | B90: BMEB4 | C90: Bancos | D90: 123728626 | E90: =D90*P90 -> 9898290080 | F90: 1200000000 | G90: =P90/L90 -> 8.2485751 | H90: 6.2 | I90: =(G90/H90-1) -> 0.33041533 | J90: 0.301 | K90: 0 | L90: =F90/D90 -> 9.6986448 | M90: 0.3 | N90: =M90*L90 -> 2.9095935 | O90: =N90/P90 -> 0.036369918 | P90: =IFERROR(__xludf.DUMMYFUNCTION("GOOGLEFINANCE(""BVMF:BMEB4"")"),80.0) -> 80 | Q90: =N90/0.0755 -> 38.537662 | R90: =1-(P90/Q90) -> -1.0758914 | S90: Semestral | T90: fevereiro e ago | U90: 46091
A91: Copasa | B91: CSMG3 | C91: Saneamento | D91: 379181000 | E91: =D91*P91 -> 19743954670 | F91: 1500000000 | G91: =P91/L91 -> 13.162636 | H91: 9.1 | I91: =(G91/H91-1) -> 0.44644357 | J91: 0.107 | K91: 2.1 | L91: =F91/D91 -> 3.9558944 | M91: 0.42 | N91: =M91*L91 -> 1.6614757 | O91: =N91/P91 -> 0.031908501 | P91: =IFERROR(__xludf.DUMMYFUNCTION("GOOGLEFINANCE(""BVMF:CSMG3"")"),52.07) -> 52.07 | Q91: =N91/0.0755 -> 22.0063 | R91: =1-(P91/Q91) -> -1.3661406 | S91: Trimestral | T91: mar, jun, set e dez | U91: 46091
A92: Brasilagro | B92: AGRO3 | C92: Agronegócio | D92: 99615457 | E92: =D92*P92 -> 2221424691 | F92: 100000000 | G92: =P92/L92 -> 22.214247 | H92: 11 | I92: =(G92/H92-1) -> 1.019477 | J92: 0.228 | K92: 1.7 | L92: =F92/D92 -> 1.0038603 | M92: 0.65 | N92: =M92*L92 -> 0.65250918 | O92: =N92/P92 -> 0.029260501 | P92: =IFERROR(__xludf.DUMMYFUNCTION("GOOGLEFINANCE(""BVMF:AGRO3"")"),22.3) -> 22.3 | Q92: =N92/0.0755 -> 8.6425057 | R92: =1-(P92/Q92) -> -1.5802702 | S92: Anual | T92: outubro | U92: 46091
A93: BTG | B93: BPAC11 | C93: Bancos | D93: 11642630400 | E93: =D93*P93/3 -> 213875120448 | F93: 20000000000 | G93: =P93/L93 -> 10.693756 | H93: 17.4 | I93: =(G93/H93-1) -> -0.38541632 | J93: 0.1966 | K93: 0 | L93: =F93*3/D93 -> 5.1534746 | M93: 0.28 | N93: =M93*L93 -> 1.4429729 | O93: =N93/P93 -> 0.026183504 | P93: =IFERROR(__xludf.DUMMYFUNCTION("GOOGLEFINANCE(""BVMF:BPAC11"")"),55.11) -> 55.11 | Q93: =N93/0.0755 -> 19.112224 | R93: =1-(P93/Q93) -> -1.8834949 | S93: Quadrimestral | T93: jan ago e dez | U93: 46091

Sheet Renda projetiva
A1: Vídeo da planilha: | B1: PLANILHA para os MEMBROS: QUAIS AS DIFERENÇAS? E FORMAS DE UTILIZAR
A3: Ticker | B3: Qtd. de ações | C3: Dividendo por ação | D3: Renda anual esperada | E3: Capital alocado | F3: Dividend Yield | H3: Ano | I3: Renda Anual | J3: Renda Mensal | K3: Taxa de crescimento (vs ano anterior)
A4: CEBR5 | B4: 34000 | C4: =VLOOKUP(A4,Dados!B2:Q105,13,FALSE) -> 2.1586526 | D4: =B4*C4 -> 73394.19 | E4: =VLOOKUP(A4,Dados!B2:R105,15,FALSE)*B4 -> 990760 | F4: =D4/E4 -> 0.074078677 | H4: 2026 | I4: =D22 -> 277237.22 | J4: =I4/12 -> 23103.102
A5: BBSE3 | B5: 13100 | C5: =VLOOKUP(A5,Dados!B2:Q105,13,FALSE) -> 3.9212557 | D5: =B5*C5 -> 51368.449 | E5: =VLOOKUP(A5,Dados!B2:R105,15,FALSE)*B5 -> 459155 | F5: =D5/E5 -> 0.11187605 | H5: 2027 | I5: =I4*(1+K5) -> 346546.53 | J5: =I5/12 -> 28878.877 | K5: 0.25
A6: EMAE4 | B6: 14700 | C6: =VLOOKUP(A6,Dados!B2:Q105,13,FALSE) -> 2.1652638 | D6: =B6*C6 -> 31829.377 | E6: =VLOOKUP(A6,Dados!B2:R105,15,FALSE)*B6 -> 654150 | F6: =D6/E6 -> 0.048657613 | H6: 2028 | I6: =I5*(1+K6) -> 415855.83 | J6: =I6/12 -> 34654.653 | K6: 0.2
A7: BBAS3 | B7: 20000 | C7: =VLOOKUP(A7,Dados!B2:Q105,13,FALSE) -> 1.2612337 | D7: =B7*C7 -> 25224.674 | E7: =VLOOKUP(A7,Dados!B2:R105,15,FALSE)*B7 -> 476200 | F7: =D7/E7 -> 0.052970756 | H7: 2029 | I7: =I6*(1+K7) -> 478234.21 | J7: =I7/12 -> 39852.851 | K7: 0.15
A8: LEVE3 | B8: 6900 | C8: =VLOOKUP(A8,Dados!B2:Q105,13,FALSE) -> 3.0212706 | D8: =B8*C8 -> 20846.767 | E8: =VLOOKUP(A8,Dados!B2:R105,15,FALSE)*B8 -> 237636 | F8: =D8/E8 -> 0.087725628 | H8: 2030 | I8: =I7*(1+K8) -> 549969.34 | J8: =I8/12 -> 45830.778 | K8: 0.15
A9: RANI3 | B9: 21400 | C9: =VLOOKUP(A9,Dados!B2:Q105,13,FALSE) -> 0.68046496 | D9: =B9*C9 -> 14561.95 | E9: =VLOOKUP(A9,Dados!B2:R105,15,FALSE)*B9 -> 194740 | F9: =D9/E9 -> 0.074776369
A10: CEBR6 | B10: 6000 | C10: =VLOOKUP(A10,Dados!B2:Q105,13,FALSE) -> 2.3745179 | D10: =B10*C10 -> 14247.107 | E10: =VLOOKUP(A10,Dados!B2:R105,15,FALSE)*B10 -> 186120 | F10: =D10/E10 -> 0.076547966
A11: CXSE3 | B11: 9200 | C11: =VLOOKUP(A11,Dados!B2:Q105,13,FALSE) -> 1.41 | D11: =B11*C11 -> 12972 | E11: =VLOOKUP(A11,Dados!B2:R105,15,FALSE)*B11 -> 166888 | F11: =D11/E11 -> 0.077728776
A12: CEBR3 | B12: 6000 | C12: =VLOOKUP(A12,Dados!B2:Q105,13,FALSE) -> 2.1586526 | D12: =B12*C12 -> 12951.916 | E12: =VLOOKUP(A12,Dados!B2:R105,15,FALSE)*B12 -> 187200 | F12: =D12/E12 -> 0.069187585
A13: CGAS5 | B13: 1100 | C13: =VLOOKUP(A13,Dados!B2:Q105,13,FALSE) -> 10.262524 | D13: =B13*C13 -> 11288.777 | E13: =VLOOKUP(A13,Dados!B2:R105,15,FALSE)*B13 -> 144980 | F13: =D13/E13 -> 0.077864374
A14: FESA4 | B14: 20700 | C14: =VLOOKUP(A14,Dados!B2:Q105,13,FALSE) -> 0.41314071 | D14: =B14*C14 -> 8552.0126 | E14: =VLOOKUP(A14,Dados!B2:R105,15,FALSE)*B14 -> 153387 | F14: =D14/E14 -> 0.055754481
C22: Renda anual esperada | D22: =SUM(D4:D21) -> 277237.22
C23: Renda média mensal | D23: =D22/12 -> 23103.102
C25: Patrimônio | D25: =SUM(E4:E21) -> 3851216
C26: Dividend Yield esperado | D26: =D22/D25 -> 0.071986931

Sheet Holding
A1: Link do vídeo: | B1: MÁQUINA de GERAR DINHEIRO? VEJA A SUA CARTEIRA COMO UMA HOLDING!
A3: Ticker | B3: Qtd. de ações | C3: Lucro por ação | D3: Lucro anual esperado | E3: Capital alocado | F3: Earning Yield | H3: Ano | I3: Lucro Anual | J3: Lucro médio mensal | K3: Taxa de crescimento (vs ano anterior)
A4: CEBR5 | B4: 34000 | C4: =VLOOKUP(A4,Dados!B2:Q105,11,FALSE) -> 2.7746178 | D4: =B4*C4 -> 94337.005 | E4: =VLOOKUP(A4,Dados!B2:R105,15,FALSE)*B4 -> 990760 | F4: =D4/E4 -> 0.095216808 | H4: 2026 | I4: =D24 -> 442447.49 | J4: =I4/12 -> 36870.624
A5: BBAS3 | B5: 20000 | C5: =VLOOKUP(A5,Dados!B2:Q105,11,FALSE) -> 4.2041124 | D5: =B5*C5 -> 84082.247 | E5: =VLOOKUP(A5,Dados!B2:R105,15,FALSE)*B5 -> 476200 | F5: =D5/E5 -> 0.17656919 | H5: 2027 | I5: =I4*(1+K5) -> 553059.36 | J5: =I5/12 -> 46088.28 | K5: 0.25
A6: EMAE4 | B6: 14700 | C6: =VLOOKUP(A6,Dados!B2:Q105,11,FALSE) -> 5.4131594 | D6: =B6*C6 -> 79573.443 | E6: =VLOOKUP(A6,Dados!B2:R105,15,FALSE)*B6 -> 654150 | F6: =D6/E6 -> 0.12164403 | H6: 2028 | I6: =I5*(1+K6) -> 663671.24 | J6: =I6/12 -> 55305.936 | K6: 0.2
A7: BBSE3 | B7: 13100 | C7: =VLOOKUP(A7,Dados!B2:Q105,11,FALSE) -> 4.4559724 | D7: =B7*C7 -> 58373.238 | E7: =VLOOKUP(A7,Dados!B2:R105,15,FALSE)*B7 -> 459155 | F7: =D7/E7 -> 0.12713188 | H7: 2029 | I7: =I6*(1+K7) -> 763221.92 | J7: =I7/12 -> 63601.827 | K7: 0.15
A8: LEVE3 | B8: 6900 | C8: =VLOOKUP(A8,Dados!B2:Q105,11,FALSE) -> 4.6481087 | D8: =B8*C8 -> 32071.95 | E8: =VLOOKUP(A8,Dados!B2:R105,15,FALSE)*B8 -> 237636 | F8: =D8/E8 -> 0.1349625 | H8: 2030 | I8: =I7*(1+K8) -> 877705.21 | J8: =I8/12 -> 73142.101 | K8: 0.15
A9: RANI3 | B9: 21400 | C9: =VLOOKUP(A9,Dados!B2:Q105,11,FALSE) -> 0.9720928 | D9: =B9*C9 -> 20802.786 | E9: =VLOOKUP(A9,Dados!B2:R105,15,FALSE)*B9 -> 194740 | F9: =D9/E9 -> 0.10682338
A10: CEBR6 | B10: 6000 | C10: =VLOOKUP(A10,Dados!B2:Q105,11,FALSE) -> 2.7746178 | D10: =B10*C10 -> 16647.707 | E10: =VLOOKUP(A10,Dados!B2:R105,15,FALSE)*B10 -> 186120 | F10: =D10/E10 -> 0.089446093
A11: CEBR3 | B11: 6000 | C11: =VLOOKUP(A11,Dados!B2:Q105,11,FALSE) -> 2.7746178 | D11: =B11*C11 -> 16647.707 | E11: =VLOOKUP(A11,Dados!B2:R105,15,FALSE)*B11 -> 187200 | F11: =D11/E11 -> 0.088930058
A12: CXSE3 | B12: 9200 | C12: =VLOOKUP(A12,Dados!B2:Q105,11,FALSE) -> 1.5666667 | D12: =B12*C12 -> 14413.333 | E12: =VLOOKUP(A12,Dados!B2:R105,15,FALSE)*B12 -> 166888 | F12: =D12/E12 -> 0.086365307
A13: CGAS5 | B13: 1100 | C13: =VLOOKUP(A13,Dados!B2:Q105,11,FALSE) -> 12.073558 | D13: =B13*C13 -> 13280.914 | E13: =VLOOKUP(A13,Dados!B2:R105,15,FALSE)*B13 -> 144980 | F13: =D13/E13 -> 0.091605145
A14: FESA4 | B14: 20700 | C14: =VLOOKUP(A14,Dados!B2:Q105,11,FALSE) -> 0.59020101 | D14: =B14*C14 -> 12217.161 | E14: =VLOOKUP(A14,Dados!B2:R105,15,FALSE)*B14 -> 153387 | F14: =D14/E14 -> 0.079649259
C24: Lucro esperado 2026 | D24: =SUM(D4:D23) -> 442447.49
C25: Lucro médio mensal | D25: =D24/12 -> 36870.624
C26: Lucro médio diário | D26: =D24/365 -> 1212.1849
C27: Patrimônio | D27: =SUM(E4:E23) -> 3851216
C28: Earning Yield esperado | D28: =D24/D27 -> 0.11488514

Sheet Calculadoras
A1: Link das Calculadoras
A4: Juros compostos | B4: Calculadora de Juros Compostos - Investidor10
A6: Primeiro milhão | B6: Calculadora do Primeiro Milhão
A8: Vídeo para entender na prática: | B8: ✅ QUANTO TEMPO PARA ATINGIR O PRIMEIRO MILHÃO? QUANTO VOCÊ PRECISARÁ INVESTIR? AÇÕES e INVESTIMENTOS
